Workbook

Sheet Wage Percentage
B1: RESTAURANT WAGE % CALCULATION SHEET
A2: LOCATION: THE ROCKS | B2: WEEK ENDING: | C2: 07/09/2026
A3: Average Hourly Rate = $ | B3: HOURS
A4: Ordinary 1x | B4: ='Costing sheet'!D51 | C4: ='Costing sheet'!E51
A5: Saturday 1.25x | B5: ='Costing sheet'!F51 | C5: ='Costing sheet'!G51
A6: Sunday 1.5x | B6: ='Costing sheet'!H51 | C6: ='Costing sheet'!I51 | Z6: 4.6
A7: Over Time 1.5x | B7: ='Costing sheet'!J51 | C7: ='Costing sheet'!K51
A8: Over Time 1.75x | B8: ='Costing sheet'!L51 | C8: ='Costing sheet'!M51
A9: Saturday / Milko | B9: ='Costing sheet'!N51 | C9: ='Costing sheet'!O51
A10: Over Time 2x | B10: ='Costing sheet'!P51 | C10: ='Costing sheet'!Q51
A11: P/Holiday 2.25x / 2.5x | B11: ='Costing sheet'!R51+'Costing sheet'!T51 | C11: ='Costing sheet'!S51+'Costing sheet'!U51
A12: Sick Leave | B12: ='Costing sheet'!V51 | C12: ='Costing sheet'!W51
A13: Split / Laundry / clothing Allowances | C13: ='Costing sheet'!Z51+'Costing sheet'!AF51
A14: Penalty Allowances 10-12am / 12-6am | C14: =SUM('Costing sheet'!AC51,'Costing sheet'!AE51)
A15: Supervisor / Public Holiday Allowances | C15: ='Costing sheet'!AA51
A16: Paid Annual Leave | B16: ='Costing sheet'!X51 | C16: ='Costing sheet'!Y51
A17: TOTAL | B17: =SUM(B4:B16) | C17: =SUM(C4:C16)
A19: Cleaning
A20: Promotions
A21: Annual Leave/termination pay | B21: =B16 | C21: =C16 | G21: `
A22: Transfer In from (BH) | B22: =Transfers!AA77 | C22: =Transfers!AB77
A23: Transfer IN from (NM) | B23: =Transfers!AA64 | C23: =Transfers!AB64
A24: Transfer IN from (DSQ) | B24: =Transfers!AA51 | C24: =Transfers!AB51
A25: Transfer OUT to (DSQ) | B25: =Transfers!AA12 | C25: =Transfers!AB12
A26: Transfer OUT to (BH) | Z26: 4.6
A27: Transfer OUT to (BH) | B27: =Transfers!AA23 | C27: =Transfers!AB23 | Z27: 4.6
A28: Transfer OUT to (NM) | B28: =Transfers!AA33 | C28: =Transfers!AB33 | Z28: 4.6
A30: Superannuation | B30: =B17*0.12 | C30: =C17*0.12
A31: Leave Liability | B31: =B17*7.69/100 | C31: =C17*7.69/100
A32: TOTAL WAGES | B32: =B17+B22+B23+B24-B25-B26-B27-B28+B31-B21+B18 | C32: =C17+C22+C23+C24-C25-C26-C27-C28+C30+C31-C21+C18
A34: Sick Leave | B34: =B12 | C34: =C12
A35: Leave Liability | B35: =B31 | C35: =C31
A36: Training | C36: 0
A37: Total Hours For Productivity | B37: =B32-(B34+B35+B36)
A38: GROSS TOTAL | B38: 117324.85
A39: Nett SALES (-GST) | B39: =B38/1.1
A40: CUSTOMERS | B40: 4500 | R40: =78875-68645.72
A41: WAGE % TO GROSS TOTAL | B41: =C32/B38
A42: WAGE % TO NETT TOTAL | B42: =C32/B39
A43: PRODUCTIVITY | B43: =B40/B37
A44: AVERAGE HOURLY RATE | B44: =C32/B37

Sheet Adjustments
C1: PAYROLL ADJUSTMENT FORM
A2: POTR | B2: WEEK ENDING: | C2: ='Wage Percentage'!C2
A3: NUMBER | B3: NAME | C3: ADJUSTMENT TO BE MADE
B4: TERMINATE
I9: 0
B10: NEW STARTER
B21: BACKPAY
B28: CHANGE TO CASUAL

Sheet Costing sheet
A1: ='Wage Percentage'!C2 | D1: THE ROCKS
J2: HOURLY COSTING | Z2: Allowances | AC2: 2.95 | AE2: 4.42 | AF2: 11.2
A3: EMPLOYEE | C3: RATE | D3: 1 | E3: $ | F3: 1.25 | G3: $ | H3: 1.5 | I3: $ | J3: 1.5 | K3: $ | L3: 1.75 | M3: $ | N3: 2 | O3: $ | P3: 2 | Q3: $ | R3: 2.25 | S3: $ | T3: 2.5 | U3: $ | V3: Sick | W3: $ | X3: Holiday | Y3: $ | Z3: Laundry | AA3: Superv. | AB3: Penalty | AC3: $ | AE3: $ | AF3: Split | AG3: TOTAL | AH3: TOTAL
D4: ORD | F4: SAT | H4: SUN | J4: O/T | L4: O/T | N4: sat2-7am | P4: O/T | R4: (PH) | T4: (PH)
F5: ORD CAS | H5: SAT CAS | L5: SUN CAS | T5: CAS
A6: AKTER, Nasrin | B6: 2 | C6: 27.08 | D6: 7.5 | E6: =C6*D6 | F6: 10 | G6: =C6*1.25*F6 | H6: 5 | I6: =C6*1.5*H6 | K6: =C6*1.5*J6 | M6: =C6*1.75*L6 | O6: =C6*2*N6 | Q6: =C6*2*P6 | S6: =C6*2.25*R6 | W6: =C6*V6 | Y6: =C6*X6 | Z6: 6.9 | AC6: =AB6*2.95 | AE6: =AD6*4.42 | AF6: =11.2*2 | AG6: =D6+F6+H6+J6+L6+P6+R6+V6+X6+N6 | AH6: =E6+G6+I6+K6+M6+Q6+S6+Z6+AA6+W6+Y6+AC6+AE6+AF6+O6+U6
A7: BANTHIA, Jiya | B7: 2 | C7: 27.08 | D7: 10 | E7: =C7*D7 | F7: 7.5 | G7: =C7*1.25*F7 | H7: 8.75 | I7: =C7*1.5*H7 | K7: =C7*1.5*J7 | M7: =C7*1.75*L7 | O7: =C7*2*N7 | Q7: =C7*2*P7 | S7: =C7*2.25*R7 | U7: =C7*2.5*T7 | W7: =C7*V7 | Y7: =C7*X7 | Z7: 6.9 | AB7: 2 | AC7: =AB7*2.95 | AE7: =AD7*4.42 | AF7: 11.2 | AG7: =D7+F7+H7+J7+L7+P7+R7+V7+X7+N7+T7 | AH7: =E7+G7+I7+K7+M7+Q7+S7+Z7+AA7+W7+Y7+AC7+AE7+AF7+O7
A8: BHATTARAI, Abisekh | B8: 2 | C8: 27.08 | D8: 12.5 | E8: =C8*D8 | F8: 7.25 | G8: =C8*1.25*F8 | H8: 0.25 | I8: =C8*1.5*H8 | K8: =C8*1.5*J8 | M8: =C8*1.75*L8 | O8: =C8*2*N8 | Q8: =C8*2*P8 | S8: =C8*2.25*R8 | U8: =C8*2.5*T8 | V8: 5 | W8: =C8*V8 | Y8: =C8*X8 | Z8: 6.9 | AB8: 2 | AC8: =AB8*2.95 | AD8: 1 | AE8: =AD8*4.42 | AG8: =D8+F8+H8+J8+L8+P8+R8+V8+X8+N8+T8 | AH8: =E8+G8+I8+K8+M8+Q8+S8+Z8+AA8+W8+Y8+AC8+AE8+AF8+O8
A9: B.K, Sanjay | B9: 2 | C9: 27.08 | D9: 17.5 | E9: =C9*D9 | F9: 9.5 | G9: =C9*1.25*F9 | H9: 9.5 | I9: =C9*1.5*H9 | K9: =C9*1.5*J9 | M9: =C9*1.75*L9 | O9: =C9*2*N9 | Q9: =C9*2*P9 | S9: =C9*2.25*R9 | W9: =C9*V9 | Y9: =C9*X9 | Z9: 6.9 | AB9: 4 | AC9: =AB9*2.95 | AD9: 1 | AE9: =AD9*4.42 | AG9: =D9+F9+H9+J9+L9+P9+R9+V9+X9+N9 | AH9: =E9+G9+I9+K9+M9+Q9+S9+Z9+AA9+W9+Y9+AC9+AE9+AF9+O9
A10: BOSC, Melissa | B10: 2 | C10: 27.08 | E10: =C10*D10 | G10: =C10*1.25*F10 | I10: =C10*1.5*H10 | K10: =C10*1.5*J10 | M10: =C10*1.75*L10 | O10: =C10*2*N10 | Q10: =C10*2*P10 | S10: =C10*2.25*R10 | W10: =C10*V10 | Y10: =C10*X10 | AC10: =AB10*2.95 | AE10: =AD10*4.42 | AG10: =D10+F10+H10+J10+L10+P10+R10+V10+X10+N10 | AH10: =E10+G10+I10+K10+M10+Q10+S10+Z10+AA10+W10+Y10+AC10+AE10+AF10+O10
A11: BUTTERS, Gary | B11: SUP | C11: 29.45 | D11: 16 | E11: =C11*D11 | F11: 7.5 | G11: =C11*1.25*F11 | H11: 8.5 | I11: =C11*1.5*H11 | K11: =C11*1.5*J11 | M11: =C11*1.75*L11 | O11: =C11*2*N11 | Q11: =C11*2*P11 | S11: =C11*2.25*R11 | W11: =C11*V11 | X11: 6 | Y11: =C11*X11 | Z11: 6.9 | AA11: 30 | AB11: 2 | AC11: =AB11*2.95 | AE11: =AD11*4.42 | AG11: =D11+F11+H11+J11+L11+P11+R11+V11+X11+N11 | AH11: =E11+G11+I11+K11+M11+Q11+S11+Z11+AA11+W11+Y11+AC11+AE11+AF11+O11
A12: CHAULAGAIN, Unisha | B12: 2 | C12: 27.08 | D12: 15 | E12: =C12*D12 | F12: 8 | G12: =C12*1.25*F12 | H12: 9.5 | I12: =C12*1.5*H12 | K12: =C12*1.5*J12 | M12: =C12*1.75*L12 | N12: 0.5 | O12: =C12*2*N12 | Q12: =C12*2*P12 | S12: =C12*2.25*R12 | U12: =C12*2.5*T12 | W12: =C12*V12 | Y12: =C12*X12 | Z12: 6.9 | AB12: 2 | AC12: =AB12*2.95 | AD12: 1 | AE12: =AD12*4.42 | AF12: 11.2 | AG12: =D12+F12+H12+J12+L12+P12+R12+V12+X12+N12+T12 | AH12: =E12+G12+I12+K12+M12+Q12+S12+Z12+AA12+W12+Y12+AC12+AE12+AF12+O12
A13: DALSANIYA, Vismay | B13: 2 | C13: 27.97 | D13: 23 | E13: =C13*D13 | F13: 8 | G13: =C13*1.25*F13 | H13: 7.5 | I13: =C13*1.5*H13 | J13: 1 | K13: =C13*1.5*J13 | M13: =C13*1.75*L13 | O13: =C13*2*N13 | Q13: =C13*2*P13 | S13: =C13*2.25*R13 | W13: =C13*V13 | Y13: =C13*X13 | Z13: 6.9 | AB13: 2 | AC13: =AB13*2.95 | AD13: 1 | AE13: =AD13*4.42 | AG13: =D13+F13+H13+J13+L13+P13+R13+V13+X13+N13 | AH13: =E13+G13+I13+K13+M13+Q13+S13+Z13+AA13+W13+Y13+AC13+AE13+AF13+O13
A14: DUTTA Pinake | B14: SAL | C14: 45.55 | D14: 41.75 | E14: =C14*D14 | G14: =C14*1.25*F14 | I14: =C14*1.5*H14 | K14: =C14*1.5*J14 | M14: =C14*1.75*L14 | O14: =C14*2*N14 | Q14: =C14*2*P14 | S14: =C14*2.25*R14 | W14: =C14*V14 | Y14: =C14*X14 | Z14: 15 | AC14: =AB14*2.95 | AE14: =AD14*4.42 | AG14: =(D14+F14+H14+J14+L14+P14+R14+V14+X14+N14)+(J15+L15+P15+R15) | AH14: =(E14+G14+I14+K14+M14+Q14+S14+Z14+AA14+W14+Y14+AC14+AE14+AF14+O14)+(K15+M15+Q15+S15)
C15: 31.3 | K15: =C15*1.5*J15 | M15: =C15*1.75*L15 | Q15: =C15*2*P15 | S15: =C15*2.25*R15 | AC15: =AB15*2.95 | AE15: =AD15*4.42
A16: FAN, Yong (Richard) | B16: SUP | C16: 29.45 | E16: =C16*D16 | F16: 2 | G16: =C16*1.25*F16 | H16: 3.5 | I16: =C16*1.5*H16 | K16: =C16*1.5*J16 | M16: =C16*1.75*L16 | O16: =C16*2*N16 | Q16: =C16*2*P16 | S16: =C16*2.25*R16 | U16: =C16*2.5*T16 | Z16: 4.6 | AC16: =AB16*2.95 | AE16: =AD16*4.42 | AG16: =D16+F16+H16+J16+L16+P16+R16+V16+X16+N16+T16 | AH16: =E16+G16+I16+K16+M16+Q16+S16+Z16+AA16+W16+Y16+AC16+AE16+AF16+O16+U16
A17: FEIGE, Oliver | B17: CAS | C17: 18.51 | G17: =C17*1.25*F17 | I17: =C17*1.5*H17 | K17: =C17*1.5*J17 | M17: =C17*1.75*L17 | O17: =C17*2*N17 | Q17: =C17*2*P17 | U17: =C17*2.5*T17 | AC17: =AB17*2.95 | AE17: =AD17*4.42 | AG17: =D17+F17+H17+J17+L17+P17+R17+V17+X17+N17+T17 | AH17: =E17+G17+I17+K17+M17+Q17+S17+Z17+AA17+W17+Y17+AC17+AE17+AF17+O17+U17
A18: FERNANDES, Delisha | B18: SAL | C18: 39.48 | D18: 22 | E18: =C18*D18 | G18: =C18*1.25*F18 | I18: =C18*1.5*H18 | K18: =C18*1.5*J18 | M18: =C18*1.75*L18 | O18: =C18*2*N18 | Q18: =C18*2*P18 | S18: =C18*2.25*R18 | W18: =C18*V18 | X18: 16 | Y18: =C18*X18 | Z18: 15 | AC18: =AB18*2.95 | AE18: =AD18*4.42 | AG18: =(D18+F18+H18+J18+L18+P18+R18+V18+X18+N18)+(J19+L19+P19+R19) | AH18: =(E18+G18+I18+K18+M18+Q18+S18+Z18+AA18+W18+Y18+AC18+AE18+AF18+O18)+(K19+M19+Q19+S19)
C19: 29.45 | K19: =C19*1.5*J19 | M19: =C19*1.75*L19 | Q19: =C19*2*P19 | S19: =C19*2.25*R19 | AC19: =AB19*2.95 | AE19: =AD19*4.42
A20: GAUCHAN, Bibek | B20: SAL | C20: 37.45 | E20: =C20*D20 | G20: =C20*1.25*F20 | I20: =C20*1.5*H20 | K20: =C20*1.5*J20 | M20: =C20*1.75*L20 | O20: =C20*2*N20 | Q20: =C20*2*P20 | S20: =C20*2.25*R20 | W20: =C20*V20 | X20: 38 | Y20: =C20*X20 | AC20: =AB20*2.95 | AE20: =AD20*4.42 | AG20: =(D20+F20+H20+J20+L20+P20+R20+V20+X20+N20)+(J21+L21+P21+R21) | AH20: =(E20+G20+I20+K20+M20+Q20+S20+Z20+AA20+W20+Y20+AC20+AE20+AF20+O20)+(K21+M21+Q21+S21)
C21: 29.45 | K21: =C21*1.5*J21 | M21: =C21*1.75*L21 | Q21: =C21*2*P21 | S21: =C21*2.25*R21 | AC21: =AB21*2.95 | AE21: =AD21*4.42
A22: GAUCHAN, Roshani | B22: SAL | C22: 37.45 | D22: 38.25 | E22: =C22*D22 | G22: =C22*1.25*F22 | I22: =C22*1.5*H22 | K22: =C22*1.5*J22 | M22: =C22*1.75*L22 | O22: =C22*2*N22 | Q22: =C22*2*P22 | S22: =C22*2.25*R22 | W22: =C22*V22 | Y22: =C22*X22 | Z22: 15 | AC22: =AB22*2.95 | AE22: =AD22*4.42 | AG22: =(D22+F22+H22+J22+L22+P22+R22+V22+X22+N22)+(J23+L23+P23+R23) | AH22: =(E22+G22+I22+K22+M22+Q22+S22+Z22+AA22+W22+Y22+AC22+AE22+AF22+O22)+(K23+M23+Q23+S23)
C23: 29.45 | K23: =C23*1.5*J23 | M23: =C23*1.75*L23 | Q23: =C23*2*P23 | S23: =C23*2.25*R23 | W23: =C23*V23 | AC23: =AB23*2.95 | AE23: =AD23*4.42
A24: JAHAN, Nusrat | B24: 2 | C24: 27.08 | D24: 17.5 | E24: =C24*D24 | F24: 7.5 | G24: =C24*1.25*F24 | H24: 7.5 | I24: =C24*1.5*H24 | K24: =C24*1.5*J24 | L24: 2 | M24: =C24*1.75*L24 | O24: =C24*2*N24 | P24: 0.75 | Q24: =C24*2*P24 | S24: =C24*2.25*R24 | U24: =C24*2.5*T24 | W24: =C24*V24 | Y24: =C24*X24 | Z24: 6.9 | AC24: =AB24*2.95 | AE24: =AD24*4.42 | AF24: 22.4 | AG24: =D24+F24+H24+J24+L24+P24+R24+V24+X24+N24+T24 | AH24: =E24+G24+I24+K24+M24+Q24+S24+Z24+AA24+W24+Y24+AC24+AE24+AF24+O24
A25: KC Anisha | B25: 2 | C25: 27.97 | D25: 21 | E25: =C25*D25 | F25: 8 | G25: =C25*1.25*F25 | H25: 8 | I25: =C25*1.5*H25 | K25: =C25*1.5*J25 | M25: =C25*1.75*L25 | O25: =C25*2*N25 | Q25: =C25*2*P25 | S25: =C25*2.25*R25 | W25: =C25*V25 | Y25: =C25*X25 | Z25: 6.9 | AB25: 2 | AC25: =AB25*2.95 | AD25: 1 | AE25: =AD25*4.42 | AG25: =D25+F25+H25+J25+L25+P25+R25+V25+X25+N25 | AH25: =E25+G25+I25+K25+M25+Q25+S25+Z25+AA25+W25+Y25+AC25+AE25+AF25+O25
A26: KC Sulav | B26: SAL | C26: 37.45 | E26: =C26*D26 | G26: =C26*1.25*F26 | I26: =C26*1.5*H26 | K26: =C26*1.5*J26 | M26: =C26*1.75*L26 | O26: =C26*2*N26 | Q26: =C26*2*P26 | S26: =C26*2.25*R26 | W26: =C26*V26 | X26: 38 | Y26: =C26*X26 | AC26: =AB26*2.95 | AE26: =AD26*4.42 | AG26: =(D26+F26+H26+J26+L26+P26+R26+V26+X26+N26)+(J27+L27+P27+R27) | AH26: =(E26+G26+I26+K26+M26+Q26+S26+Z26+AA26+W26+Y26+AC26+AE26+AF26+O26)+(K27+M27+Q27+S27)
C27: 29.45 | K27: =C27*1.5*J27 | M27: =C27*1.75*L27 | Q27: =C27*2*P27 | S27: =C27*2.25*R27 | AC27: =AB27*2.95 | AE27: =AD27*4.42
A28: KHATRI, Sanjay | B28: SAL | C28: 37.45 | D28: 36.5 | E28: =C28*D28 | G28: =C28*1.25*F28 | I28: =C28*1.5*H28 | K28: =C28*1.5*J28 | M28: =C28*1.75*L28 | O28: =C28*2*N28 | Q28: =C28*2*P28 | S28: =C28*2.25*R28 | V28: 1.5 | W28: =C28*V28 | Y28: =C28*X28 | Z28: 15 | AC28: =AB28*2.95 | AE28: =AD28*4.42 | AG28: =(D28+F28+H28+J28+L28+P28+R28+V28+X28+N28)+(J29+L29+P29+R29) | AH28: =(E28+G28+I28+K28+M28+Q28+S28+Z28+AA28+W28+Y28+AC28+AE28+AF28+O28)+(K29+M29+Q29+S29)
C29: 29.45 | K29: =C29*1.5*J29 | M29: =C29*1.75*L29 | Q29: =C29*2*P29 | S29: =C29*2.25*R29 | AC29: =AB29*2.95 | AE29: =AD29*4.42
A30: MAHMUD M M Ferdous | B30: SAL | C30: 37.45 | D30: 37.5 | E30: =C30*D30 | G30: =C30*1.25*F30 | I30: =C30*1.5*H30 | K30: =C30*1.5*J30 | M30: =C30*1.75*L30 | O30: =C30*2*N30 | Q30: =C30*2*P30 | S30: =C30*2.25*R30 | W30: =C30*V30 | X30: 0.5 | Y30: =C30*X30 | Z30: 15 | AC30: =AB30*2.95 | AE30: =AD30*4.42 | AG30: =(D30+F30+H30+J30+L30+P30+R30+V30+X30+N30)+(J31+L31+P31+R31) | AH30: =(E30+G30+I30+K30+M30+Q30+S30+Z30+AA30+W30+Y30+AC30+AE30+AF30+O30)+(K31+M31+Q31+S31)
C31: 29.45 | K31: =C31*1.5*J31 | M31: =C31*1.75*L31 | Q31: =C31*2*P31 | S31: =C31*2.25*R31 | AC31: =AB31*2.95 | AE31: =AD31*4.42
A32: MAJOHR, Jolie | B32: 2 | C32: 27.08 | E32: =C32*D32 | G32: =C32*1.25*F32 | H32: 5 | I32: =C32*1.5*H32 | K32: =C32*1.5*J32 | L32: 7 | M32: =C32*1.75*L32 | O32: =C32*2*N32 | Q32: =C32*2*P32 | S32: =C32*2.25*R32 | W32: =C32*V32 | Y32: =C32*X32 | Z32: 4.6 | AC32: =AB32*2.95 | AE32: =AD32*4.42 | AG32: =D32+F32+H32+J32+L32+P32+R32+V32+X32+N32 | AH32: =E32+G32+I32+K32+M32+Q32+S32+Z32+AA32+W32+Y32+AC32+AE32+AF32+O32+U32
A33: MALLA, Kajal | B33: 2 | C33: 27.08 | D33: 20.5 | E33: =C33*D33 | F33: 7.5 | G33: =C33*1.25*F33 | H33: 5 | I33: =C33*1.5*H33 | K33: =C33*1.5*J33 | M33: =C33*1.75*L33 | O33: =C33*2*N33 | Q33: =C33*2*P33 | S33: =C33*2.25*R33 | W33: =C33*V33 | Y33: =C33*X33 | Z33: 6.9 | AC33: =AB33*2.95 | AE33: =AD33*4.42 | AF33: 11.2 | AG33: =D33+F33+H33+J33+L33+P33+R33+V33+X33+N33 | AH33: =E33+G33+I33+K33+M33+Q33+S33+Z33+AA33+W33+Y33+AC33+AE33+AF33+O33
A34: RAHMAN, Mahinur | B34: 2 | C34: 27.08 | E34: =C34*D34 | G34: =C34*1.25*F34 | I34: =C34*1.5*H34 | K34: =C34*1.5*J34 | M34: =C34*1.75*L34 | O34: =C34*2*N34 | Q34: =C34*2*P34 | S34: =C34*2.25*R34 | U34: =C34*2.5*T34 | W34: =C34*V34 | Y34: =C34*X34 | AC34: =AB34*2.95 | AE34: =AD34*4.42 | AG34: =D34+F34+H34+J34+L34+P34+R34+T34+X34+N34 | AH34: =E34+G34+I34+K34+M34+Q34+S34+Z34+AA34+U34+Y34+AC34+AE34+AF34+O34
A35: RANA, Royal | B35: 2 | C35: 27.08 | D35: 21.5 | E35: =C35*D35 | F35: 5 | G35: =C35*1.25*F35 | I35: =C35*1.5*H35 | K35: =C35*1.5*J35 | M35: =C35*1.75*L35 | O35: =C35*2*N35 | Q35: =C35*2*P35 | S35: =C35*2.25*R35 | U35: =C35*2.5*T35 | W35: =C35*V35 | Y35: =C35*X35 | Z35: 6.9 | AB35: 4 | AC35: =AB35*2.95 | AD35: 2 | AE35: =AD35*4.42 | AG35: =D35+F35+H35+J35+L35+P35+R35+V35+X35+N35+T35 | AH35: =E35+G35+I35+K35+M35+Q35+S35+Z35+AA35+W35+Y35+AC35+AE35+AF35+O35
A36: SAHA, Oyndrilla | B36: SUP | C36: 29.45 | D36: 11 | E36: =C36*D36 | F36: 5 | G36: =C36*1.25*F36 | H36: 7.5 | I36: =C36*1.5*H36 | K36: =C36*1.5*J36 | M36: =C36*1.75*L36 | O36: =C36*2*N36 | Q36: =C36*2*P36 | S36: =C36*2.25*R36 | W36: =C36*V36 | Y36: =C36*X36 | Z36: 6.9 | AC36: =AB36*2.95 | AE36: =AD36*4.42 | AG36: =D36+F36+H36+J36+L36+P36+R36+V36+X36+N36 | AH36: =E36+G36+I36+K36+M36+Q36+S36+Z36+AA36+W36+Y36+AC36+AE36+AF36+O36
A37: SAIYED, Wasim | B37: SAL | C37: 36.81 | D37: 30.25 | E37: =C37*D37 | G37: =C37*1.25*F37 | I37: =C37*1.5*H37 | K37: =C37*1.5*J37 | M37: =C37*1.75*L37 | O37: =C37*2*N37 | Q37: =C37*2*P37 | S37: =C37*2.25*R37 | W37: =C37*V37 | X37: 7.75 | Y37: =C37*X37 | Z37: 15 | AC37: =AB37*2.95 | AE37: =AD37*4.42 | AG37: =(D37+F37+H37+J37+L37+P37+R37+V37+X37+N37)+(J38+L38+P38+R38) | AH37: =(E37+G37+I37+K37+M37+Q37+S37+Z37+AA37+W37+Y37+AC37+AE37+AF37+O37)+(K38+M38+Q38+S38)
C38: 29.45 | K38: =C38*1.5*J38 | M38: =C38*1.75*L38 | Q38: =C38*2*P38 | S38: =C38*2.25*R38 | AC38: =AB38*2.95 | AE38: =AD38*4.42
A39: SAMIT, Satwat Hossain | B39: 2 | C39: 27.97 | D39: 25.5 | E39: =C39*D39 | F39: 5 | G39: =C39*1.25*F39 | H39: 7.5 | I39: =C39*1.5*H39 | K39: =C39*1.5*J39 | M39: =C39*1.75*L39 | O39: =C39*2*N39 | P39: 0.25 | Q39: =C39*2*P39 | S39: =C39*2.25*R39 | W39: =C39*V39 | Y39: =C39*X39 | Z39: 6.9 | AC39: =AB39*2.95 | AE39: =AD39*4.42 | AG39: =D39+F39+H39+J39+L39+P39+R39+V39+X39+N39 | AH39: =E39+G39+I39+K39+M39+Q39+S39+Z39+AA39+W39+Y39+AC39+AE39+AF39+O39
A40: SHIWAKOTI, Rojal | B40: SUP | C40: 29.85 | D40: 7 | E40: =C40*D40 | F40: 7.5 | G40: =C40*1.25*F40 | H40: 10 | I40: =C40*1.5*H40 | K40: =C40*1.5*J40 | M40: =C40*1.75*L40 | O40: =C40*2*N40 | P40: 0.25 | Q40: =C40*2*P40 | S40: =C40*2.25*R40 | W40: =C40*V40 | Y40: =C40*X40 | Z40: 6.9 | AA40: 15 | AB40: 2 | AC40: =AB40*2.95 | AD40: 1 | AE40: =AD40*4.42 | AF40: 11.2 | AG40: =D40+F40+H40+J40+L40+P40+R40+V40+X40+N40 | AH40: =E40+G40+I40+K40+M40+Q40+S40+Z40+AA40+W40+Y40+AC40+AE40+AF40+O40
A41: SHRESTHA, Anish | B41: 2 | C41: 27.08 | D41: 10 | E41: =C41*D41 | F41: 5 | G41: =C41*1.25*F41 | H41: 5 | I41: =C41*1.5*H41 | J41: 1.75 | K41: =C41*1.5*J41 | M41: =C41*1.75*L41 | O41: =C41*2*N41 | Q41: =C41*2*P41 | S41: =C41*2.25*R41 | W41: =C41*V41 | Y41: =C41*X41 | Z41: 6.9 | AC41: =AB41*2.95 | AE41: =AD41*4.42 | AG41: =D41+F41+H41+J41+L41+P41+R41+V41+X41+N41 | AH41: =E41+G41+I41+K41+M41+Q41+S41+Z41+AA41+W41+Y41+AC41+AE41+AF41+O41+U41
A42: SHRESTHA, Nikita | B42: SAL | C42: 37.45 | D42: 39 | E42: =C42*D42 | G42: =C42*1.25*F42 | I42: =C42*1.5*H42 | K42: =C42*1.5*J42 | M42: =C42*1.75*L42 | O42: =C42*2*N42 | Q42: =C42*2*P42 | S42: =C42*2.25*R42 | W42: =C42*V42 | Y42: =C42*X42 | Z42: 15 | AC42: =AB42*2.95 | AE42: =AD42*4.42 | AG42: =(D42+F42+H42+J42+L42+P42+R42+V42+X42+N42)+(J43+L43+P43+R43) | AH42: =(E42+G42+I42+K42+M42+Q42+S42+Z42+AA42+W42+Y42+AC42+AE42+AF42+O42)+(K43+M43+Q43+S43)
C43: 29.45 | K43: =C43*1.5*J43 | M43: =C43*1.75*L43 | Q43: =C43*2*P43 | S43: =C43*2.25*R43 | AC43: =AB43*2.95 | AE43: =AD43*4.42
A44: SHRESTHA Rojan | B44: SAL | C44: 37.45 | D44: 42 | E44: =C44*D44 | G44: =C44*1.25*F44 | I44: =C44*1.5*H44 | K44: =C44*1.5*J44 | M44: =C44*1.75*L44 | O44: =C44*2*N44 | Q44: =C44*2*P44 | S44: =C44*2.25*R44 | W44: =C44*V44 | Y44: =C44*X44 | Z44: 15 | AC44: =AB44*2.95 | AE44: =AD44*4.42 | AG44: =(D44+F44+H44+J44+L44+P44+R44+V44+X44+N44)+(J45+L45+P45+R45) | AH44: =(E44+G44+I44+K44+M44+Q44+S44+Z44+AA44+W44+Y44+AC44+AE44+AF44+O44)+(K45+M45+Q45+S45)
C45: 29.45 | K45: =C45*1.5*J45 | M45: =C45*1.75*L45 | Q45: =C45*2*P45 | S45: =C45*2.25*R45 | AC45: =AB45*2.95 | AE45: =AD45*4.42
A46: SHRESTHA, Roji | B46: 2 | C46: 27.08 | D46: 10 | E46: =C46*D46 | F46: 7.5 | G46: =C46*1.25*F46 | H46: 7.5 | I46: =C46*1.5*H46 | K46: =C46*1.5*J46 | M46: =C46*1.75*L46 | O46: =C46*2*N46 | P46: 1 | Q46: =C46*2*P46 | S46: =C46*2.25*R46 | U46: =C46*2.5*T46 | W46: =C46*V46 | Y46: =C46*X46 | Z46: 6.9 | AB46: 1 | AC46: =AB46*2.95 | AE46: =AD46*4.42 | AG46: =D46+F46+H46+J46+L46+P46+R46+V46+X46+N46+T46 | AH46: =E46+G46+I46+K46+M46+Q46+S46+Z46+AA46+W46+Y46+AC46+AE46+AF46+O46
A47: TAMANG, Chandraman | B47: CAS | C47: 27.97 | F47: 16 | G47: =C47*1.25*F47 | H47: 6 | I47: =C47*1.5*H47 | K47: =C47*1.5*J47 | L47: 9.5 | M47: =C47*1.75*L47 | N47: 0.25 | O47: =C47*2*N47 | Q47: =C47*2*P47 | U47: =C47*2.5*T47 | Z47: 6.9 | AB47: 2 | AC47: =AB47*2.95 | AE47: =AD47*4.42 | AG47: =D47+F47+H47+J47+L47+P47+R47+V47+X47+N47+T47 | AH47: =E47+G47+I47+K47+M47+Q47+S47+Z47+AA47+W47+Y47+AC47+AE47+AF47+O47+U47
A48: TAMANG, Prajwol | B48: 2 | C48: 27.08 | D48: 9.5 | E48: =C48*D48 | F48: 5 | G48: =C48*1.25*F48 | I48: =C48*1.5*H48 | K48: =C48*1.5*J48 | M48: =C48*1.75*L48 | O48: =C48*2*N48 | Q48: =C48*2*P48 | S48: =C48*2.25*R48 | W48: =C48*V48 | Y48: =C48*X48 | Z48: 4.6 | AB48: 1 | AC48: =AB48*2.95 | AE48: =AD48*4.42 | AG48: =D48+F48+H48+J48+L48+P48+R48+V48+X48+N48 | AH48: =E48+G48+I48+K48+M48+Q48+S48+Z48+AA48+W48+Y48+AC48+AE48+AF48+O48+U48
A49: THAPALIYA, Sirish | B49: CAS | C49: 27.97 | E49: =C49*D49 | F49: 17.5 | G49: =C49*1.25*F49 | H49: 7.5 | I49: =C49*1.5*H49 | K49: =C49*1.5*J49 | L49: 6.5 | M49: =C49*1.75*L49 | O49: =C49*2*N49 | Q49: =C49*2*P49 | S49: =C49*2.25*R49 | U49: =C49*2.5*T49 | W49: =C49*V49 | Y49: =C49*X49 | Z49: 6.9 | AC49: =AB49*2.95 | AE49: =AD49*4.42 | AG49: =D49+F49+H49+J49+L49+P49+R49+V49+X49+N49+T49 | AH49: =E49+G49+I49+K49+M49+Q49+S49+U49+Z49+AA49+W49+Y49+AC49+AE49+AF49+O49
A50: TIRTHO, Rafid Mahmud | B50: 2 | C50: 27.97 | D50: 20 | E50: =C50*D50 | F50: 8 | G50: =C50*1.25*F50 | H50: 9.5 | I50: =C50*1.5*H50 | J50: 1.5 | K50: 1.5 | M50: =C50*1.75*L50 | N50: 0.5 | O50: =C50*2*N50 | Q50: =C50*2*P50 | S50: =C50*2.25*R50 | W50: =C50*V50 | Y50: =C50*X50 | Z50: 6.9 | AB50: 6 | AC50: =AB50*2.95 | AD50: 2 | AE50: =AD50*4.42 | AG50: =D50+F50+H50+J50+L50+P50+R50+V50+X50+N50 | AH50: =E50+G50+I50+K50+M50+Q50+S50+Z50+AA50+W50+Y50+AC50+AE50+AF50+O50
D51: =SUM(D6:D50) | E51: =SUM(E5:E50) | F51: =SUM(F5:F50) | G51: =SUM(G5:G50) | H51: =SUM(H5:H50) | I51: =SUM(I5:I50) | J51: =SUM(J5:J50) | K51: =SUM(K5:K50) | L51: =SUM(L5:L50) | ... Y51: =SUM(Y5:Y50) | Z51: =SUM(Z6:Z50) | AA51: =SUM(AA5:AA50) | AB51: =SUM(AB5:AB50) | AC51: =SUM(AC5:AC50) | AD51: =SUM(AD5:AD50) | AE51: =SUM(AE5:AE50) | AF51: =SUM(AF5:AF50) | AG51: =SUM(AG6:AG50) | AH51: =SUM(AH6:AH50)
C52: CHECK | D52: =D51-('Data Sheet'!B50/100) | F52: =F51-('Data Sheet'!C50/100) | H52: =H51-('Data Sheet'!D50/100) | J52: =J51-('Data Sheet'!E50/100) | L52: =L51-('Data Sheet'!F50/100) | N52: =N51-('Data Sheet'!G50/100) | P52: =P51-('Data Sheet'!H50/100) | R52: =R51-('Data Sheet'!I50/100) | T52: =T51-('Data Sheet'!J50/100) | V52: =V51-('Data Sheet'!K50/100) | X52: =X51-('Data Sheet'!L50/100) | Z52: =(Z51+AA51)-('Data Sheet'!M50+'Data Sheet'!N50) | AB52: =AB51-'Data Sheet'!O50 | AD52: =AD51-'Data Sheet'!P50 | AF52: =AF52-'Data Sheet'!#REF! | AG52: =D51+F51+H51+J51+L51+P51+R51+V51+X51+N51+T51 | AH52: =AF51+G51+AC51+AE51+AA51+Z51+Y51+W51+S51+Q51+M51+K51+I51+E51+O51+U51

Sheet Data Sheet
A1: POTR - THE ROCKS | B1: ='Wage Percentage'!C2
A2: EMPLOYEE | C2: SAT | D2: SUN | E2: O/Time | F2: O/Time | G2: Sat Milko 2.0 | H2: O/Time | I2: P/Hol | J2: P/Hol | K2: Sick | L2: Annual | M2: LAUN | N2: SUPER | O2: PEN | P2: PEN | Q2: Split | R2: TOTAL
A3: NAME | B3: ORD | C3: 1.25 | D3: 1.5 | E3: 1.5 | F3: 1.75 | H3: 2 | I3: 2.25 | J3: 2.5 | K3: Leave | L3: Leave | M3: Allow | N3: Allow | O3: 10-12am | P3: 12-6am | Q3: Allow
C4: ORD CAS | D4: SAT CAS | F4: SUN CAS | J4: CAS | Q4: 11.2
A5: AKTER, Nasrin | B5: 750 | C5: 1000 | D5: 500 | M5: 3 | Q5: 22.4 | R5: =B5+C5+D5+E5+F5+G5+H5+I5+K5+L5+J5
A6: BANTHIA, Jiya | B6: 1000 | C6: 750 | D6: 875 | M6: 3 | O6: 2 | Q6: 11.2 | R6: =B6+C6+D6+E6+F6+G6+H6+I6+K6+L6+J6
A7: BHATTARAI, Abisekh | B7: 1250 | C7: 725 | D7: 25 | K7: 500 | M7: 3 | O7: 2 | P7: 1 | R7: =B7+C7+D7+E7+F7+G7+H7+I7+K7+L7+J7
A8: B.K, Sanjay | B8: 1750 | C8: 950 | D8: 950 | M8: 3 | O8: 4 | P8: 1 | R8: =B8+C8+D8+E8+F8+G8+H8+I8+K8+L8
A9: BOSC, Melissa | R9: =B9+C9+D9+E9+F9+G9+H9+I9+K9+L9+J9
A10: BUTTERS, Gary | B10: 1600 | C10: 750 | D10: 850 | L10: 600 | M10: 3 | N10: 30 | O10: 2 | R10: =B10+C10+D10+E10+F10+G10+H10+I10+K10+L10
A11: CHAULAGAIN, Unisha | B11: 1500 | C11: 800 | D11: 950 | G11: 50 | M11: 3 | O11: 2 | P11: 1 | Q11: 11.2 | R11: =B11+C11+D11+E11+F11+G11+H11+I11+K11+L11+J11
A12: DALSANIYA, Vismay | B12: 2300 | C12: 800 | D12: 750 | E12: 100 | M12: 3 | O12: 2 | P12: 1 | R12: =B12+C12+D12+E12+F12+G12+H12+I12+K12+L12+J12
A13: DUTTA Pinake | B13: 4175 | M13: 15 | R13: =(B13+C13+D13+E13+F13+G13+H13+I13+K13+L13+J13)+(E14+F14+H14+I14)
A15: FAN, Yong (Richard) | C15: 200 | D15: 350 | M15: 2 | R15: =B15+C15+D15+E15+F15+G15+H15+I15+K15+L15+J15
A16: FEIGE, Oliver | R16: =B16+C16+D16+E16+F16+G16+H16+I16+K16+L16+J16
A17: FERNANDES, Delisha | B17: 2200 | L17: 1600 | M17: 15 | R17: =(B17+C17+D17+E17+F17+G17+H17+I17+K17+L17+J17)+(E18+F18+H18+I18)
A19: GAUCHAN Bibek | L19: 3800 | R19: =(B19+C19+D19+E19+F19+G19+H19+I19+K19+L19+J19)+(E20+F20+H20+I20)
A21: GAUCHAN Roshani | B21: 3825 | M21: 15 | R21: =(B21+C21+D21+E21+F21+G21+H21+I21+K21+L21+J21)+(E22+F22+H22+I22)
A23: JAHAN, Nusrat | B23: 1750 | C23: 750 | D23: 750 | F23: 200 | H23: 75 | M23: 3 | Q23: 22.4 | R23: =B23+C23+D23+E23+F23+G23+H23+I23+K23+L23+J23
A24: KC Anisha | B24: 2100 | C24: 800 | D24: 800 | M24: 3 | O24: 2 | P24: 1 | R24: =B24+C24+D24+E24+F24+G24+H24+I24+K24+L24+J24
A25: KCSulav | L25: 3800 | R25: =(B25+C25+D25+E25+F25+G25+H25+I25+K25+L25+J25)+(E26+F26+H26+I26)
A27: KHATRI, Sanjay | B27: 3650 | K27: 150 | M27: 15 | R27: =(B27+C27+D27+E27+F27+G27+H27+I27+K27+L27+J27)+(E28+F28+H28+I28)
A29: MAHMUD M M Ferdous | B29: 3750 | L29: 50 | M29: 15 | R29: =(B29+C29+D29+E29+F29+G29+H29+I29+K29+L29+J29)+(E30+F30+H30+I30)
A31: MAJOHR, Jolie | D31: 500 | F31: 700 | M31: 2 | R31: =B31+C31+D31+E31+F31+G31+H31+I31+K31+L31+J31
A32: MALLA, Kajal | B32: 2050 | C32: 750 | D32: 500 | M32: 3 | Q32: 11.2 | R32: =B32+C32+D32+E32+F32+G32+H32+I32+K32+L32+J32
A33: RAHMAN, Mahinur | R33: =B33+C33+D33+E33+F33+G33+H33+I33+K33+L33
A34: RANA, Royal | B34: 2150 | C34: 500 | M34: 3 | O34: 4 | P34: 2 | R34: =B34+C34+D34+E34+F34+G34+H34+I34+K34+L34+J34
A35: SAHA, Oyndrilla | B35: 1100 | C35: 500 | D35: 750 | M35: 3 | R35: =B35+C35+D35+E35+F35+G35+H35+I35+K35+L35
A36: SAIYED Wasim | B36: 3025 | L36: 775 | M36: 15 | R36: =(B36+C36+D36+E36+F36+G36+H36+I36+K36+L36+J36)+(E37+F37+H37+I37)
A38: SAMIT, Satwat Hossain | B38: 2550 | C38: 500 | D38: 750 | H38: 25 | M38: 3 | R38: =B38+C38+D38+E38+F38+G38+H38+I38+L38+J38+K38
A39: SHIWAKOTI Rojal | B39: 700 | C39: 750 | D39: 1000 | H39: 25 | M39: 3 | N39: 15 | O39: 2 | P39: 1 | Q39: 11.2 | R39: =B39+C39+D39+E39+F39+G39+H39+I39+K39+L39+J39
A40: SHRESTHA, Anish | B40: 1000 | C40: 500 | D40: 500 | E40: 175 | M40: 3 | R40: =B40+C40+D40+E40+F40+G40+H40+I40+K40+L40+J40
A41: SHRESTHA Nikita | B41: 3900 | M41: 15 | R41: =(B41+C41+D41+E41+F41+G41+H41+I41+K41+L41+J41)+(E42+F42+H42+I42)
A43: SHRESTHA Rojan | B43: 4200 | M43: 15 | R43: =(B43+C43+D43+E43+F43+G43+H43+I43+K43+L43+J43)+(E44+F44+H44+I44)
A45: SHRESTHA, Roji | B45: 1000 | C45: 750 | D45: 750 | H45: 100 | M45: 3 | O45: 1 | R45: =B45+C45+D45+E45+F45+G45+H45+I45+K45+L45+J45
A46: TAMANG, Chandraman | C46: 1600 | D46: 600 | F46: 950 | G46: 25 | M46: 3 | O46: 2 | R46: =B46+C46+D46+E46+F46+G46+H46+I46+K46+L46+J46
A47: TAMANG, Prajwol | B47: 950 | C47: 500 | M47: 2 | O47: 1 | R47: =B47+C47+D47+E47+F47+G47+H47+I47+K47+L47+J47
A48: THAPALIYA, Sirish | C48: 1750 | D48: 750 | F48: 650 | M48: 3 | R48: =B48+C48+D48+E48+F48+G48+H48+I48+K48+L48+J48
A49: TIRTHO, Rafid Mahmud | B49: 2000 | C49: 800 | D49: 950 | E49: 150 | G49: 50 | M49: 3 | O49: 6 | P49: 2 | R49: =B49+C49+D49+E49+F49+G49+H49+I49+K49+L49+J49
B50: =SUM(B5:B49) | C50: =SUM(C5:C49) | D50: =SUM(D5:D49) | E50: =SUM(E5:E49) | F50: =SUM(F5:F49) | G50: =SUM(G5:G49) | H50: =SUM(H5:H49) | I50: =SUM(I5:I49) | J50: =SUM(J7:J49) | K50: =SUM(K5:K49) | L50: =SUM(L5:L49) | M50: =SUM(M5:M12,M15:M16,M23:M24,M31:M35,M38:M40,M45:M49)*2.3+(M13+M17+M21+M29+M36+M41+M43+M25+M27+M19) | N50: =SUM(N5:N49) | O50: =SUM(O5:O49) | P50: =SUM(P5:P49) | Q50: =SUM(Q5:Q49) | R50: =SUM(R5:R49)

Sheet Salary Costing Sheet
A1: ='Data Sheet'!B1 | D1: THE ROCKS
K2: HOURLY COSTING | V2: Allowances | Y2: 2.95 | AA2: 4.42 | AB2: 11.2
A3: EMPLOYEE | C3: RATE | D3: 1 | E3: $ | F3: 1.25 | H3: 1.5 | I3: $ | J3: 1.5 | K3: $ | L3: 1.75 | M3: $ | N3: 2 | O3: $ | P3: 2.25 | Q3: $ | R3: Sick | S3: $ | T3: Holiday | U3: $ | V3: Laundry | W3: Superv. | X3: Penalty | Y3: $ | Z3: Penalty | AA3: $ | AB3: Split | AC3: TOTAL | AD3: TOTAL
D4: ORD | F4: SAT | H4: SUN | J4: OT | L4: O/Time | N4: O/Time OR sat milko | P4: P/Hol | R4: Leave | V4: Clothing | W4: P/Hol | X4: 10-12pm | Z4: 12-7am | AB4: Shift | AC4: HOURS | AD4: $'s
A5: DUTTA PINAKE | C5: 31.3 | D5: 22.25 | E5: =C5*D5 | F5: 6.5 | G5: =F5*C5*1.25 | H5: 9 | I5: =C5*1.5*H5 | K5: =C5*1.5*J5 | M5: =C5*1.75*L5 | N5: 4 | O5: =C5*2*N5 | Q5: =C5*2.25*P5 | S5: =C5*R5 | U5: =C5*T5 | V5: 6.9 | W5: 45 | X5: 2 | Y5: =X5*2.95 | Z5: 1 | AA5: =Z5*4.42 | AC5: =D5+F5+H5+J5+L5+N5+P5+R5+T5 | AD5: =E5+G5+I5+K5+M5+O5+Q5+V5+W5+S5+U5+Y5+AA5+AB5
A6: FERNANDES, Delisha | C6: 29.45 | D6: 21.5 | E6: =C6*D6 | F6: 0.5 | G6: =F6*C6*1.25 | I6: =C6*1.5*H6 | K6: =C6*1.5*J6 | M6: =C6*1.75*L6 | O6: =C6*2*N6 | Q6: =C6*2.25*P6 | S6: =C6*R6 | T6: 16 | U6: =C6*T6 | V6: 6.9 | W6: 15 | X6: 6 | Y6: =X6*2.95 | AA6: =Z6*4.42 | AC6: =D6+F6+H6+J6+L6+N6+P6+R6+T6 | AD6: =E6+G6+I6+K6+M6+O6+Q6+V6+W6+S6+U6+Y6+AA6+AB6
A7: GAUCHAN, Bibek | C7: 29.45 | E7: =C7*D7 | G7: =F7*C7*1.25 | I7: =C7*1.5*H7 | K7: =C7*1.5*J7 | M7: =C7*1.75*L7 | O7: =C7*2*N7 | Q7: =C7*2.25*P7 | S7: =C7*R7 | T7: 38 | U7: =C7*T7 | Y7: =X7*2.95 | AA7: =Z7*4.42 | AC7: =D7+F7+H7+J7+L7+N7+P7+R7+T7 | AD7: =E7+G7+I7+K7+M7+O7+Q7+V7+W7+S7+U7+Y7+AA7+AB7
A8: GAUCHAN, Roshani | C8: 29.45 | D8: 32 | E8: =C8*D8 | F8: 6 | G8: =F8*C8*1.25 | I8: =C8*1.5*H8 | J8: 0.25 | K8: =C8*1.5*J8 | M8: =C8*1.75*L8 | O8: =C8*2*N8 | Q8: =C8*2.25*P8 | S8: =C8*R8 | U8: =C8*T8 | V8: 6.9 | Y8: =X8*2.95 | AA8: =Z8*4.42 | AC8: =D8+F8+H8+J8+L8+N8+P8+R8+T8 | AD8: =E8+G8+I8+K8+M8+O8+Q8+V8+W8+S8+U8+Y8+AA8+AB8
A9: KC Sulav | C9: 29.45 | E9: =C9*D9 | G9: =F9*C9*1.25 | I9: =C9*1.5*H9 | K9: =C9*1.5*J9 | M9: =C9*1.75*L9 | O9: =C9*2*N9 | Q9: =C9*2.25*P9 | S9: =C9*R9 | T9: 38 | U9: =C9*T9 | Y9: =X9*2.95 | AA9: =Z9*4.42 | AC9: =D9+F9+H9+J9+L9+N9+P9+R9+T9 | AD9: =E9+G9+I9+K9+M9+O9+Q9+V9+W9+S9+U9+Y9+AA9+AB9
A10: KHATRI, Sanjay | C10: 29.45 | D10: 23.5 | E10: =C10*D10 | F10: 7 | G10: =F10*C10*1.25 | H10: 6 | I10: =C10*1.5*H10 | K10: =C10*1.5*J10 | M10: =C10*1.75*L10 | O10: =C10*2*N10 | Q10: =C10*2.25*P10 | R10: 1.5 | S10: =C10*R10 | U10: =C10*T10 | V10: 6.9 | Y10: =X10*2.95 | AA10: =Z10*4.42 | AC10: =D10+F10+H10+J10+L10+N10+P10+R10+T10 | AD10: =E10+G10+I10+K10+M10+O10+Q10+V10+W10+S10+U10+Y10+AA10+AB10
A11: MAHMUD M M FERDOUS | C11: 29.45 | D11: 22 | E11: =C11*D11 | F11: 7.5 | G11: =F11*C11*1.25 | H11: 8 | I11: =C11*1.5*H11 | K11: =C11*1.5*J11 | M11: =C11*1.75*L11 | O11: =C11*2*N11 | Q11: =C11*2.25*P11 | S11: =C11*R11 | T11: 0.5 | U11: =C11*T11 | V11: 6.9 | Y11: =X11*2.95 | AA11: =Z11*4.42 | AC11: =D11+F11+H11+J11+L11+N11+P11+R11+T11 | AD11: =E11+G11+I11+K11+M11+O11+Q11+V11+W11+S11+U11+Y11+AA11+AB11
A12: SAIYED WASIM | C12: 29.45 | D12: 16 | E12: =C12*D12 | F12: 7.5 | G12: =F12*C12*1.25 | H12: 6.75 | I12: =C12*1.5*H12 | K12: =C12*1.5*J12 | M12: =C12*1.75*L12 | O12: =C12*2*N12 | Q12: =C12*2.25*P12 | S12: =C12*R12 | T12: 7.75 | U12: =C12*T12 | V12: 6.9 | X12: 4 | Y12: =X12*2.95 | Z12: 1 | AA12: =Z12*4.42 | AC12: =D12+F12+H12+J12+L12+N12+P12+R12+T12 | AD12: =E12+G12+I12+K12+M12+O12+Q12+V12+W12+S12+U12+Y12+AA12+AB12
A13: SHRESTHA, Nikita | C13: 29.45 | D13: 24 | E13: =C13*D13 | F13: 8 | G13: =F13*C13*1.25 | H13: 6 | I13: =C13*1.5*H13 | K13: =C13*1.5*J13 | M13: =C13*1.75*L13 | N13: 1 | O13: =C13*2*N13 | Q13: =C13*2.25*P13 | S13: =C13*R13 | U13: =C13*T13 | V13: 6.9 | W13: 45 | X13: 4 | Y13: =X13*2.95 | Z13: 1 | AA13: =Z13*4.42 | AC13: =D13+F13+H13+J13+L13+N13+P13+R13+T13 | AD13: =E13+G13+I13+K13+M13+O13+Q13+V13+W13+S13+U13+Y13+AA13+AB13
A14: SHRESTHA, Rojan | C14: 29.45 | D14: 22 | E14: =C14*D14 | F14: 6.5 | G14: =F14*C14*1.25 | H14: 9.5 | I14: =C14*1.5*H14 | J14: 2 | K14: =C14*1.5*J14 | M14: =C14*1.75*L14 | N14: 2 | O14: =C14*2*N14 | Q14: =C14*2.25*P14 | S14: =C14*R14 | U14: =C14*T14 | V14: 6.9 | X14: 1 | Y14: =X14*2.95 | AA14: =Z14*4.42 | AC14: =D14+F14+H14+J14+L14+N14+P14+R14+T14 | AD14: =E14+G14+I14+K14+M14+O14+Q14+V14+W14+S14+U14+Y14+AA14+AB14
D15: =SUM(D5:D14) | E15: =SUM(E5:E14) | F15: =SUM(F5:F14) | G15: =SUM(G5:G14) | H15: =SUM(H5:H14) | I15: =SUM(I5:I14) | J15: =SUM(J5:J14) | K15: =SUM(K5:K14) | ... AC15: =SUM(AC5:AC14) | AD15: =E15+I15+K15+M15+O15+Q15+V15+W15+S15+U15+Y15+AA15+AB15+G15
AB16: Check - | AC16: =D15+H15+J15+L15+N15+P15+R15+T15+F15 | AD16: =AB15+Y15+AA15+W15+V15+U15+S15+Q15+O15+M15+K15+I15+E15
C35: `

Sheet Proj VS Actual
C6: 42736
B10: 42373 | C10: 42737 | E10: 42380 | F10: 42744 | H10: 42387 | I10: 42751
B11: Last Year | C11: Projected | D11: Actual | E11: Last Year | F11: Projected | G11: Actual | H11: Last Year | I11: Projected | J11: Actual
A12: GROSS TOTAL | B12: 286926.8 | C12: 302722 | D12: 299560 | E12: 197704.39 | F12: 194160 | G12: 210706.33 | H12: 168782.39 | I12: 170258 | J12: 168047.44
A13: NETT TOTAL | B13: =B12/1.1 | C13: =C12/1.1 | D13: =D12/1.1 | E13: =E12/1.1 | F13: =F12/1.1 | G13: =G12/1.1 | H13: =H12/1.1 | I13: =I12/1.1 | J13: =J12/1.1
A14: Customers | B14: 13426 | C14: 12990 | D14: 13376 | E14: 9668 | F14: 9525 | G14: 10184 | H14: 8274 | I14: 8300 | J14: 8007
A15: Average Customer Spend | B15: =B12/B14 | C15: =C12/C14 | D15: =D12/D14 | E15: =E12/E14 | F15: =F12/F14 | G15: =G12/G14 | H15: =H12/H14 | I15: =I12/I14 | J15: =J12/J14
A16: Wage % to Gross total | B16: =(B19*B20)/B12 | C16: =(C19*C20)/C12 | D16: =(D19*D20)/D12 | E16: =(E19*E20)/E12 | F16: =(F19*F20)/F12 | G16: =(G19*G20)/G12 | H16: =(H19*H20)/H12 | I16: =(I19*I20)/I12 | J16: =(J19*J20)/J12
A17: Wage % to Nett Total | B17: =(B19*B20)/B13 | C17: =(C19*C20)/C13 | D17: =(D19*D20)/D13 | E17: =(E19*E20)/E13 | F17: =(F19*F20)/F13 | G17: =(G19*G20)/G13 | H17: =(H19*H20)/H13 | I17: =(I19*I20)/I13 | J17: =(J19*J20)/J13
A18: Productivity | B18: =B14/B20 | C18: =C14/C20 | D18: =D14/D20 | E18: =E14/E20 | F18: =F14/F20 | G18: =G14/G20 | H18: =H14/H20 | I18: =I14/I20 | J18: =J14/J20
A19: Average Hourly Rate | B19: 34.75 | C19: 41 | D19: 41.02 | E19: 30.3 | F19: 30 | G19: 30.7 | H19: 30.22 | I19: 30 | J19: 30.57
A20: Total hours for productivity | B20: 2287.75 | C20: 2223.5 | D20: 2301.5 | E20: 1944.25 | F20: 1729.5 | G20: 1804.25 | H20: 1759 | I20: 1567 | J20: 1685.25
A21: Training Hours used | B21: 0 | C21: 0 | D21: 0 | E21: 39 | F21: 50 | G21: 35 | H21: 0 | I21: 65.5 | J21: 95.5
A22: Number of hours used to cover sick leave | B22: 97.5 | C22: 0 | D22: 8 | E22: 81 | F22: 0 | G22: 36.5 | H22: 26.5 | I22: 0
A23: Minimum HOURS | B23: Kitchen | C23: 656 | E23: Kitchen | F23: 583 | H23: Kitchen | I23: 548
B24: Floor | C24: 1065 | E24: Floor | F24: 1001 | H24: Floor | I24: 926
B25: TOTAL | C25: =SUM(C23:C24) | E25: TOTAL | F25: =SUM(F23:F24) | H25: TOTAL | I25: =SUM(I23:I24)
F27: Details | G27: Hrs | I27: Details | J27: Hrs
F29: Ishita (CO T1-T3) | G29: 15 | I29: Sana (Sup T1-T5) | J29: 37.5
F30: Justas (Host T1-T3) | G30: 15 | I30: Rajesh (Bar T1-T3) | J30: 15
F31: Yuka (Host T1-T3) | G31: 15- CANCELLED | I31: Aga (Bar T1-T3) | J31: 15
F32: Ferdous (Invoice T1) | G32: 5 | I32: Ruta (Host T1-T3) | J32: 15
I33: Yuka (CO T1-T3) | J33: 15- CANCELLED
I34: Ferdous (Inv T2 +f/c) | J34: 13
I35: Total | J35: =SUM(J29:J34)
B36: 42394 | C36: 42758 | E36: 42401 | F36: 42765 | H36: 42408 | I36: 42772
B37: Last Year | C37: Projected | D37: Actual | E37: Last Year | F37: Projected | G37: Actual | H37: Last Year | I37: Projected | J37: Actual
A38: GROSS TOTAL | B38: 178931.17 | C38: 173236 | D38: 179658 | E38: 184512.73 | F38: 216935 | G38: 231891 | H38: 201196.62 | I38: 195285 | J38: 195050.8
A39: NETT TOTAL | B39: =B38/1.1 | C39: =C38/1.1 | D39: =D38/1.1 | E39: =E38/1.1 | F39: =F38/1.1 | G39: =G38/1.1 | H39: =H38/1.1 | I39: =I38/1.1 | J39: =J38/1.1
A40: Customers | B40: 8583 | C40: 8500 | D40: 8502 | E40: 8494 | F40: 9950 | G40: 10209 | H40: 9032 | I40: 8885 | J40: 8542
A41: Average Customer Spend | B41: =B38/B40 | C41: =C38/C40 | D41: =D38/D40 | E41: =E38/E40 | F41: =F38/F40 | G41: =G38/G40 | H41: =H38/H40 | I41: =I38/I40 | J41: =J38/J40
A42: Wage % to Gross total | B42: =(B45*B46)/B38 | C42: =(C45*C46)/C38 | D42: =(D45*D46)/D38 | E42: =(E45*E46)/E38 | F42: =(F45*F46)/F38 | G42: =(G45*G46)/G38 | H42: =(H45*H46)/H38 | I42: =(I45*I46)/I38 | J42: =(J45*J46)/J38
A43: Wage % to Nett Total | B43: =(B45*B46)/B39 | C43: =(C45*C46)/C39 | D43: =(D45*D46)/D39 | E43: =(E45*E46)/E39 | F43: =(F45*F46)/F39 | G43: =(G45*G46)/G39 | H43: =(H45*H46)/H39 | I43: =(I45*I46)/I39 | J43: =(J45*J46)/J39
A44: Productivity | B44: =B40/B46 | C44: =C40/C46 | D44: =D40/D46 | E44: =E40/E46 | F44: =F40/F46 | G44: =G40/G46 | H44: =H40/H46 | I44: =I40/I46 | J44: =J40/J46
A45: Average Hourly Rate | B45: 31.07 | C45: 30 | D45: 30.95 | E45: 35.07 | F45: 35 | G45: 35.06 | H45: 30.34 | I45: 30 | J45: 30.16
A46: Total hours for productivity | B46: 1811.25 | C46: 1664.5 | D46: 1647.25 | E46: 1766.75 | F46: 1810.5 | G46: 1908 | H46: 1720.5 | I46: 1868.5 | J46: 1798.5
A47: Training Hours used | B47: 7.5 | C47: 0 | D47: 45.5 | E47: 48.5 | G47: 89 | H47: 82.5 | I47: 281.5 | J47: 261.5
A48: Number of hours used to cover sick leave | B48: 45 | C48: 0 | E48: 39.5 | H48: 23
A49: Minimum HOURS | B49: Kitchen | C49: 545 | E49: Kitchen | F49: 584 | H49: Kitchen
B50: Floor | C50: 927 | E50: Floor | H50: Floor
B51: TOTAL | C51: =SUM(C49:C50) | E51: TOTAL | F51: =SUM(F49:F50) | H51: TOTAL | I51: =SUM(I49:I50)
C53: Details | D53: Hrs | F53: Details | G53: Hrs | I53: Details | J53: Hrs
C54: Ferdous (F/COST T2) | D54: 8 | F54: Ferdous (F/COST T3) | G54: 8 | H54: New starters(floor) | J54: 185
C55: Juan Roster T2 | D55: 7.5 | F55: Juan Roster T3 | G55: 7.5 | H55: Abbu TC T2 | J55: 3.5
C56: Chelsea Bar T1-T3 | D56: 15 | F56: Abbu TC T1 | G56: 3.5 | H56: Abbu Payroll T2 | J56: 3.5
C57: Ruta Bar T1-T3 | D57: 15 | F57: New starters(floor+kitchen) | G57: 70
H58: Ferdous (F/COST T4) | J58: 8
C59: Total | D59: =SUM(D54:D58) | F59: Total | G59: =SUM(G54:G58) | H59: Devon (Crepe T1-T2) | J59: 12
H60: Rojan (Milko T1- T2) | J60: 16
H61: Dat (Stocking T1- T2) | J61: 22.5
H62: Terry (Crepes T1 + Rol T1) | J62: 11
I63: Total | J63: =SUM(J54:J62)
B64: we 15/2/17 | D64: 42779 | E64: 42422 | F64: 42786 | H64: 42429 | I64: 42793
B65: Last Year | C65: Projected | D65: Actual | E65: Last Year | F65: Projected | G65: Actual | H65: Last Year | I65: Projected | J65: Actual
A66: GROSS TOTAL | B66: 223865 | C66: 183454 | D66: 167156.77 | E66: 179030.82 | F66: 171327 | G66: 165865.09 | H66: 160936 | I66: 162421 | J66: 157332.84
A67: NETT TOTAL | B67: =B66/1.1 | C67: =C66/1.1 | D67: =D66/1.1 | E67: =E66/1.1 | F67: =F66/1.1 | G67: =G66/1.1 | H67: =H66/1.1 | I67: =I66/1.1 | J67: =J66/1.1
A68: Customers | B68: 9782 | C68: 8375 | D68: 7646 | E68: 8263 | F68: 7790 | G68: 7827 | H68: 7684 | I68: 7720 | J68: 7729
A69: Average Customer Spend | B69: =B66/B68 | C69: =C66/C68 | D69: =D66/D68 | E69: =E66/E68 | F69: =F66/F68 | G69: =G66/G68 | H69: =H66/H68 | I69: =I66/I68 | J69: =J66/J68
A70: Wage % to Gross total | B70: =(B73*B74)/B66 | C70: =(C73*C74)/C66 | D70: =(D73*D74)/D66 | E70: =(E73*E74)/E66 | F70: =(F73*F74)/F66 | G70: =(G73*G74)/G66 | H70: =(H73*H74)/H66 | I70: =(I73*I74)/I66 | J70: =(J73*J74)/J66
A71: Wage % to Nett Total | B71: =(B73*B74)/B67 | C71: =(C73*C74)/C67 | D71: =(D73*D74)/D67 | E71: =(E73*E74)/E67 | F71: =(F73*F74)/F67 | G71: =(G73*G74)/G67 | H71: =(H73*H74)/H67 | I71: =(I73*I74)/I67 | J71: =(J73*J74)/J67
A72: Productivity | B72: =B68/B74 | C72: =C68/C74 | D72: =D68/D74 | E72: =E68/E74 | F72: =F68/F74 | G72: =G68/G74 | H72: =H68/H74 | I72: =I68/I74 | J72: =J68/J74
A73: Average Hourly Rate | B73: 31.91 | C73: 30.5 | D73: 31.17 | E73: 30.48 | F73: 30 | G73: 31.85 | H73: 31.26 | I73: 30 | J73: 32.37
A74: Total hours for productivity | B74: 1743 | C74: 1639 | D74: 1595.5 | E74: 1683.5 | F74: 1585.5 | G74: 1565.25 | H74: 1616.75 | I74: 1524 | J74: 1487.25
A75: Training Hours used | C75: 85 | D75: 80 | F75: 139.5 | G75: 89.5 | I75: 13
A76: Number of hours used to cover sick leave | C76: 0 | J76: 65
A77: Minimum HOURS | B77: Kitchen | C77: 574 | E77: Kitchen | H77: Kitchen | I77: 530
B78: Floor | C78: 986 | E78: Floor | H78: Floor | I78: 898
B79: TOTAL | C79: =SUM(C77:C78) | E79: TOTAL | F79: =SUM(F77:F78) | H79: TOTAL | I79: =SUM(I77:I78)
B81: Abbu TC T3 | D81: 1.5 | F81: Bhumika (sup)T1-T5 | G81: 39.5 | I81: Dat (prep T4 &T5) | J81: 13
B82: Abbu Payroll T3 | D82: 3.5 | F82: Chelsea(COT)T1-T3 | G82: 15
B83: New starters(floor) | D83: 4 | F83: Dat (PrepT1,T2) | G83: 15
B84: Terry Rol T2 | D84: 6 | F84: Irene(GrillT3&T4) | G84: 10
B85: Dev pizza T1+T2 | D85: 10 | F85: Dev(pizza T2,T3) | G85: 10
B86: Irene Grill T2 | D86: 10
B87: Gedas( bar) | D87: 15
B88: Aga (host) | D88: 15
B89: Chelsea (host0 | D89: 15
B91: 42436 | D91: 42800 | E91: 42443 | G91: 42807 | H91: 42815 | J91: 42814
B92: Last Year | C92: Projected | D92: Actual | E92: Last Year | F92: Projected | G92: Actual | H92: Last Year | I92: Projected | J92: Actual
A93: GROSS TOTAL | B93: 154056.07 | C93: 166544 | D93: 155071 | E93: 160962 | F93: 159092 | G93: 161699.17 | H93: 161623.72 | I93: 158609 | J93: 150677.07
A94: NETT TOTAL | B94: =B93/1.1 | C94: =C93/1.1 | D94: =D93/1.1 | E94: =E93/1.1 | F94: =F93/1.1 | G94: =G93/1.1 | H94: =H93/1.1 | I94: =I93/1.1 | J94: =J93/1.1
A95: Customers | B95: 7213 | C95: 7940 | D95: 7244 | E95: 7860 | F95: 7605 | G95: 7696 | H95: 7675 | I95: 7415 | J95: 7277
A96: Average Customer Spend | B96: =B93/B95 | C96: =C93/C95 | D96: =D93/D95 | E96: =E93/E95 | F96: =F93/F95 | G96: =G93/G95 | H96: =H93/H95 | I96: =I93/I95 | J96: =J93/J95
A97: Wage % to Gross total | B97: =(B100*B101)/B93 | C97: =(C100*C101)/C93 | D97: =(D100*D101)/D93 | E97: =(E100*E101)/E93 | F97: =(F100*F101)/F93 | G97: =(G100*G101)/G93 | H97: =(H100*H101)/H93 | I97: =(I100*I101)/I93 | J97: =(J100*J101)/J93
A98: Wage % to Nett Total | B98: =(B100*B101)/B94 | C98: =(C100*C101)/C94 | D98: =(D100*D101)/D94 | E98: =(E100*E101)/E94 | F98: =(F100*F101)/F94 | G98: =(G100*G101)/G94 | H98: =(H100*H101)/H94 | I98: =(I100*I101)/I94 | J98: =(J100*J101)/J94
A99: Productivity | B99: =B95/B101 | C99: =C95/C101 | D99: =D95/D101 | E99: =E95/E101 | F99: =F95/F101 | G99: =G95/G101 | H99: =H95/H101 | I99: =I95/I101 | J99: =J95/J101
A100: Average Hourly Rate | B100: 30.82 | C100: 31 | D100: 31.42 | E100: 31.45 | F100: 31.5 | G100: 32.47 | H100: 30.48 | I100: 31.5 | J100: 31.58
A101: Total hours for productivity | B101: 1675.5 | C101: 1475.5 | D101: 1451.75 | E101: 1653.5 | F101: 1469.5 | G101: 1406.25 | H101: 1730.25 | I101: 1473.5 | J101: 1465
A102: Training Hours used | B102: 118.5 | C102: 38 | D102: 33 | E102: 118 | F102: 20 | H102: 121.5 | I102: 75 | J102: 75
A103: Number of hours used to cover sick leave | B103: 38.75 | C103: 0 | D103: 31.5 | E103: 45 | H103: 38
A104: Minimum HOURS | B104: 628 | C104: 510 | E104: Kitchen | H104: Kitchen | I104: 445
B105: 724 | C105: 873 | E105: Floor | H105: Floor | I105: 728
B106: TOTAL | C106: =SUM(C104:C105) | E106: TOTAL | F106: =SUM(F104:F105) | H106: TOTAL | I106: =SUM(I104:I105)
B108: Keshav crepes T1 & T2 T3 | D108: 18 | H108: Ming Li (bar)T1-T3 | J108: 15
B109: keshav stocking T1 cxld | D109: 5 | H109: Denise(host) T1-T3 | J109: 15
B110: Dat prep T5 T6 | D110: 15 | H110: Vyga (Stocking T1 | J110: 7.5
H111: Justin cooking T1 | J111: 7.5
H112: keshav stocking | J112: 15
H113: Mohit B'fast T1-T2 | J113: 15
B114: 42822 | D114: 42821 | E114: 42829 | G114: 42828 | J114: 42835
...

Sheet Transfers
A1: Transfer OUT to DSQ
A2: EMPLOYEE | C2: RATE | D2: 1 | E2: $ | F2: 1.25 | G2: $ | H2: 1.5 | I2: $ | J2: 1.5 | K2: $ | L2: 1.75 | M2: $ | N2: 2 | O2: $ | P2: 2.25 | R2: 2.5 | T2: split | U2: sup | V2: laundry | X2: 2.95 | Z2: 4.42 | AA2: TOTAL | AB2: TOTAL
F3: SAT | H3: SUN | J3: O/T | L3: O/T | N3: O/T | P3: ph | R3: ph casual | W3: Penalty | X3: $ | Z3: $
A4: MALLA, Kajal | C4: 25.85 | E4: =C4*D4 | G4: =C4*1.25*F4 | I4: =C4*1.5*H4 | K4: =C4*1.5*J4 | M4: =C4*1.75*L4 | O4: =C4*2*N4 | Q4: =C4*2.25*P4 | S4: =C4*2.5*R4 | X4: =W4*X2 | Z4: =Z2*Y4 | AA4: =D4+F4+H4+J4+L4+N4+R4+P4 | AB4: =E4+G4+I4+K4+M4+O4+Z4+X4+V4+T4+Q4+S4+U4
A5: TIRTHO, Rafid Mahmud | C5: 26.7 | E5: =C5*D5 | G5: =F5*C5*F2 | I5: =C5*1.5*H5 | K5: =C5*1.5*J5 | M5: =C5*1.75*L5 | O5: =C5*2*N5 | Q5: =C5*2.25*P5 | S5: =C5*2.5*R5 | X5: =W5*X2 | Z5: =Z2*Y5 | AA5: =D5+F5+H5+J5+L5+N5+R5+P5 | AB5: =E5+G5+I5+K5+M5+O5+Z5+X5+V5+T5+Q5+S5+U5
A6: BANIYA ,Bijusha | B6: CAS | C6: 28.12 | E6: =C6*D6 | G6: =C6*1.25*F6 | I6: =C6*1.5*H6 | K6: =C6*1.5*J6 | M6: =C6*1.75*L6 | O6: =C6*2*N6 | Q6: =C6*2.25*P6 | S6: =C6*2.5*R6 | X6: =W6*X2 | Z6: =Z4*Y6 | AA6: =D6+F6+H6+J6+L6+N6+R6+P6 | AB6: =E6+G6+I6+K6+M6+O6+Z6+X6+V6+T6+Q6+S6+U6
A7: GAUCHAN, Bibek | B7: SAL | C7: 37.45 | E7: =C7*D7 | G7: =C7*1.25*F7 | I7: =C7*1.5*H7 | K7: =C7*1.5*J7 | M7: =C7*1.75*L7 | O7: =C7*2*N7 | Q7: =C7*2.25*P7 | S7: =C7*2.5*R7 | X7: =W7*X5 | Z7: =Z5*Y7 | AA7: =D7+F7+H7+J7+L7+N7+R7+P7 | AB7: =E7+G7+I7+K7+M7+O7+Z7+X7+V7+T7+Q7+S7+U7
A8: KHATRI, Sanjay | B8: SAL | C8: 37.45 | E8: =C8*D8 | G8: =C8*1.25*F8 | I8: =C8*1.5*H8 | K8: =C8*1.5*J8 | M8: =C8*1.75*L8 | O8: =C8*2*N8 | Q8: =C8*2.25*P8 | S8: =C8*2.5*R8 | X8: =W8*X6 | Z8: =Z6*Y8 | AA8: =D8+F8+H8+J8+L8+N8+R8+P8 | AB8: =E8+G8+I8+K8+M8+O8+Z8+X8+V8+T8+Q8+S8+U8
A9: KC Sulav | B9: SAL | C9: 37.45 | E9: =C9*D9 | G9: =C9*1.25*F9 | I9: =C9*1.5*H9 | K9: =C9*1.5*J9 | M9: =C9*1.75*L9 | O9: =C9*2*N9 | Q9: =C9*2.25*P9 | S9: =C9*2.5*R9 | X9: =W9*X6 | Z9: =Z6*Y9 | AA9: =D9+F9+H9+J9+L9+N9+R9+P9 | AB9: =E9+G9+I9+K9+M9+O9+Z9+X9+V9+T9+Q9+S9+U9
A10: SHIWAKOTI, Rojal | B10: SUP | C10: 28.5 | E10: =C10*D10 | G10: =C10*1.25*F10 | I10: =C10*1.5*H10 | K10: =C10*1.5*J10 | M10: =C10*1.75*L10 | O10: =C10*2*N10 | Q10: =C10*2.25*P10 | S10: =C10*2.5*R10 | X10: =W10*X7 | Z10: =Z7*Y10 | AA10: =D10+F10+H10+J10+L10+N10+R10+P10 | AB10: =E10+G10+I10+K10+M10+O10+Z10+X10+V10+T10+Q10+S10+U10
A11: FAN, Yong (Richard) | B11: CAS | C11: 29.45 | E11: =C11*D11 | G11: =C11*1.25*F11 | H11: 3.5 | I11: =C11*1.5*H11 | K11: =C11*1.5*J11 | M11: =C11*1.75*L11 | O11: =C11*2*N11 | Q11: =C11*2.25*P11 | S11: =C11*2.5*R11 | X11: =W11*X9 | Z11: =Z9*Y11 | AA11: =D11+F11+H11+J11+L11+N11+R11+P11 | AB11: =E11+G11+I11+K11+M11+O11+Z11+X11+V11+T11+Q11+S11+U11
AA12: =SUM(AA4:AA11) | AB12: =SUM(AB4:AB11)
A13: transfer OUT to BH
A14: EMPLOYEE | C14: RATE | D14: 1 | E14: $ | F14: 1.25 | G14: $ | H14: 1.5 | I14: $ | J14: 1.5 | K14: $ | L14: 1.75 | M14: $ | N14: 2 | O14: $ | P14: 2.25 | R14: 2.5 | T14: split | U14: sup | V14: laundry | W14: 10-12am | X14: 2.81 | Z14: 4.22 | AA14: TOTAL | AB14: TOTAL
F15: SAT | H15: SUN | J15: O/T | L15: O/T | N15: O/T
A16: KC, Sulav | B16: SAL | C16: 37.45 | E16: =C16*D16 | G16: =E16*F16 | I16: =C16*1.5*H16 | K16: =E16*1.5*J16 | M16: =C16*1.75*L16 | O16: =E16*1.75*N16 | Q16: =E16*2.25*P16 | S16: =C16*2.5*R16 | X16: =W16*X14 | Z16: =Y16*Z14 | AA16: =D16+P16+R16+F16+H16+J16+L16+N16 | AB16: =E16+G16+I16+K16+M16+O16+Z16+X16+V16+Q16+S16+T16+U16
A17: Khanal, Nischal | C17: 28.12 | E17: =C17*D17 | G17: =E17*F17 | I17: =C17*1.5*H17 | K17: =E17*1.5*J17 | M17: =C17*1.75*L17 | O17: =E17*1.75*N17 | Q17: =E17*2.25*P17 | S17: =C17*2.5*R17 | X17: =W17*X15 | Z17: =Y17*Z15 | AA17: =D17+P17+R17+F17+H17+J17+L17+N17 | AB17: =E17+G17+I17+K17+M17+O17+Z17+X17+V17+Q17+S17+T17+U17
A18: SHIWAKOTI, Rojal | C18: 28.5 | E18: =C18*D18 | G18: =C18*1.25*F18 | I18: =C18*1.5*H18 | K18: =C18*1.5*J18 | M18: =C18*1.75*L18 | O18: =C18*2*N18 | Q18: =C18*2.25*P18 | S18: =C18*2.5*R18 | X18: =W18*X12 | Z18: =Y18*Z11 | AA18: =D18+P18+R18+F18+H18+J18+L18+N18 | AB18: =E18+G18+I18+K18+M18+O18+Z18+X18+V18+Q18+S18+T18+U18
A19: MAJOHR, Jolie | C19: 25.85 | E19: =C19*D19 | G19: =C19*1.25*F19 | I19: =C19*1.5*H19 | K19: =C19*1.5*J19 | M19: =C19*1.75*L19 | O19: =C19*2*N19 | Q19: =C19*2.25*P19 | S19: =C19*2.5*R19 | X19: =W19*X12 | Z19: =Y19*Z11 | AA19: =D19+P19+R19+F19+H19+J19+L19+N19 | AB19: =E19+G19+I19+K19+M19+O19+Z19+X19+V19+Q19+S19+T19+U19
A20: RAHMAN, Mahinur | C20: 25.85 | E20: =C20*D20 | G20: =C20*1.25*F20 | I20: =C20*1.5*H20 | K20: =C20*1.5*J20 | M20: =C20*1.75*L20 | O20: =C20*2*N20 | Q20: =C20*2.25*P20 | S20: =C20*2.5*R20 | X20: =W20*X13 | Z20: =Y20*Z12 | AA20: =D20+P20+R20+F20+H20+J20+L20+N20 | AB20: =E20+G20+I20+K20+M20+O20+Z20+X20+V20+Q20+S20+T20+U20
A21: DISSANAYAKE, Dissanayake Mudiyanselage Hansali Nimsadi | B21: CAS | C21: 25.85 | E21: =C21*D21 | G21: =C21*1.25*F21 | I21: =C21*1.5*H21 | K21: =C21*1.5*J21 | M21: =C21*1.75*L21 | O21: =C21*2*N21 | Q21: =C21*2.25*P21 | S21: =C21*2.5*R21 | X21: =W21*X14 | Z21: =Y21*Z13 | AA21: =D21+P21+R21+F21+H21+J21+L21+N21 | AB21: =E21+G21+I21+K21+M21+O21+Z21+X21+V21+Q21+S21+T21+U21
C22: 26.7 | E22: =C22*D22 | G22: =C22*1.25*F22 | I22: =C22*1.5*H22 | K22: =C22*1.5*J22 | M22: =C22*1.75*L22 | O22: =C22*2*N22 | Q22: =C22*2.25*P22 | S22: =C22*2.5*R22 | X22: =W22*X15 | Z22: =Y22*Z14 | AA22: =D22+P22+R22+F22+H22+J22+L22+N22 | AB22: =E22+G22+I22+K22+M22+O22+Z22+X22+V22+Q22+S22+T22+U22
AA23: =SUM(AA16:AA22) | AB23: =SUM(AB16:AB22)
A24: Transfer OUT to Northmead
A25: EMPLOYEE | C25: RATE | D25: 1 | E25: $ | F25: 1.25 | G25: $ | H25: 1.5 | I25: $ | J25: 1.5 | K25: $ | L25: 1.75 | M25: $ | N25: 2 | O25: $ | P25: 2.25 | R25: 2.5 | T25: split | U25: sup | V25: laundry | X25: 2.48 | Z25: 3.71 | AA25: TOTAL | AB25: TOTAL
F26: SAT | H26: SUN | J26: O/T | L26: O/T | N26: O/T | P26: ph | R26: ph casual
E27: =C27*D27 | G27: =C27*1.25*F27 | I27: =C27*1.5*H27 | K27: =C27*1.5*J27 | M27: =C27*1.75*L27 | O27: =C27*2*N27 | Q27: =C27*2.25*P27 | S27: =C27*2.5*R27 | X27: =W27*X25 | Z27: =Y27*Z25 | AA27: =D27+F27+H27+J27+L27+N27 | AB27: =E27+G27+I27+K27+M27+O27+Z27+X27+V27+T27+Q27+S27
A28: WAGLE KHATRI, Sabina | C28: 26.7 | E28: =C28*D28 | G28: =C28*1.25*F28 | I28: =C28*1.5*H28 | K28: =C28*1.5*J28 | M28: =C28*1.75*L28 | O28: =C28*2*N28 | Q28: =C28*2.25*P28 | S28: =C28*2.5*R28 | X28: =W28*X25 | Z28: =Y28*Z25 | AA28: =D28+F28+H28+J28+L28+N28+P28 | AB28: =E28+G28+I28+K28+M28+O28+Z28+X28+V28+T28+Q28+S28
A29: PARTHO, Razin Mahmud | C29: 27.17 | E29: =C29*D29 | G29: =C29*1.25*F29 | I29: =C29*1.5*H29 | K29: =C29*1.5*J29 | M29: =C29*1.75*L29 | O29: =C29*2*N29 | Q29: =C29*2.25*P29 | S29: =C29*2.5*R29 | X29: =W29*X25 | Z29: =Y29*Z25 | AA29: =D29+F29+H29+J29+L29+N29 | AB29: =E29+G29+I29+K29+M29+O29+Z29+X29+V29+T29+Q29+S29
A30: KARTA, Vera | C30: 40 | E30: =C30*D30 | G30: =C30*1.25*F30 | I30: =C30*1.5*H30 | K30: =C30*1.5*J30 | M30: =C30*1.75*L30 | O30: =C30*2*N30 | Q30: =C30*2.25*P30 | S30: =C30*2.5*R30 | X30: =W30*X25 | Z30: =Y30*Z25 | AA30: =D30+F30+H30+J30+L30+N30 | AB30: =E30+G30+I30+K30+M30+O30+Z30+X30+V30+T30+Q30+S30
A31: Feige, Oliver | B31: cas | C31: 15.51 | E31: =C31*D31 | G31: =C31*1.25*F31 | I31: =C31*1.5*H31 | K31: =C31*1.5*J31 | M31: =C31*1.75*L31 | O31: =C31*2*N31 | Q31: =C31*2.25*P31 | S31: =C31*2.5*R31 | X31: =W31*X25 | Z31: =Y31*Z25 | AA31: =D31+F31+H31+J31+L31+N31 | AB31: =E31+G31+I31+K31+M31+O31+Z31+X31+V31+T31+Q31+S31
I32: =C32*1.5*H32 | Q32: =C32*2.25*P32 | X32: =W32*X25
AA33: =SUM(AA27:AA31) | AB33: =SUM(AB27:AB31)
A34: Transfer IN from DSQ
A35: EMPLOYEE | C35: RATE | D35: 1 | E35: $ | F35: 1.25 | G35: $ | H35: 1.5 | I35: $ | J35: 1.5 | K35: $ | L35: 1.75 | M35: $ | N35: 2 | O35: $ | P35: 2.25 | R35: Sick | S35: $ | T35: split | U35: sup | V35: laundry | X35: 2.95 | Z35: 4.42 | AA35: TOTAL | AB35: TOTAL
F36: SAT | H36: SUN | J36: O/T | L36: O/T | N36: O/T | P36: PH
A37: KHANAL, Nischal | C37: 29.45 | D37: 21.5 | E37: =C37*D37 | F37: 6.5 | G37: =C37*1.25*F37 | H37: 8.5 | I37: =C37*1.5*H37 | K37: =C37*1.5*J37 | M37: =C37*1.75*L37 | N37: 0.25 | O37: =C37*2*N37 | S37: =R37*C37 | V37: 6.9 | W37: 6 | X37: =W37*X35 | Y37: 3 | Z37: =Y37*Z35 | AA37: =D37+F37+H37+J37+L37+N37+P37+R37 | AB37: =E37+G37+I37+K37+M37+O37+Z37+X37+V37+T37+R37+Q37
A38: GODA, Yuka | B38: SAL | C38: 40.5 | E38: =C38*D38 | G38: =C38*1.25*F38 | I38: =C38*1.5*H38 | K38: =C38*1.5*J38 | M38: =C38*1.75*L38 | O38: =C38*2*N38 | X38: =W38*X35 | Z38: =Y38*Z35 | AA38: =D38+F38+H38+J38+L38+N38 | AB38: =E38+G38+I38+K38+M38+O38+Z38+X38+V38+T38
A39: MANANDHAR, Leelen | C39: 26.7 | E39: =C39*D39 | G39: =C39*1.25*F39 | I39: =C39*1.5*H39 | K39: =C39*1.5*J39 | M39: =C39*1.75*L39 | O39: =C39*2*N39 | X39: =W39*X35 | Z39: =Y39*Z35 | AA39: =D39+F39+H39+J39+L39+N39 | AB39: =E39+G39+I39+K39+M39+O39+Z39+X39+V39+T39
A40: ISKANDAR, Kenny | C40: 28.12 | E40: =C40*D40 | G40: =C40*1.25*F40 | I40: =C40*1.5*H40 | K40: =C40*1.5*J40 | M40: =C40*1.75*L40 | O40: =C40*2*N40 | X40: =W40*X35 | Z40: =Y40*Z35 | AA40: =D40+F40+H40+J40+L40+N40 | AB40: =E40+G40+I40+K40+M40+O40+Z40+X40+V40+T40
A41: KUDO, Kana | C41: 25.8 | E41: =C41*D41 | G41: =C41*1.25*F41 | I41: =C41*1.5*H41 | K41: =C41*1.5*J41 | M41: =C41*1.75*L41 | O41: =C41*2*N41 | X41: =W41*X35 | Z41: =Y41*Z35 | AA41: =D41+F41+H41+J41+L41+N41 | AB41: =E41+G41+I41+K41+M41+O41+Z41+X41+V41+T41
A42: MANANDHAR, Leelen | C42: 26.7 | E42: =C42*D42 | G42: =C42*1.25*F42 | I42: =C42*1.5*H42 | K42: =C42*1.5*J42 | M42: =C42*1.75*L42 | O42: =C42*2*N42 | X42: =W42*X35 | Z42: =Y42*Z35 | AA42: =D42+F42+H42+J42+L42+N42 | AB42: =E42+G42+I42+K42+M42+O42+Z42+X42+V42+T42
A43: SHRESTHA, Bisesh | C43: 26.7 | E43: =C43*D43 | G43: =C43*1.25*F43 | I43: =C43*1.5*H43 | K43: =C43*1.5*J43 | M43: =C43*1.75*L43 | O43: =C43*2*N43 | X43: =W43*X35 | Z43: =Y43*Z35 | AA43: =D43+F43+H43+J43+L43+N43 | AB43: =E43+G43+I43+K43+M43+O43+Z43+X43+V43+T43
A44: POLUAN, Kevin | C44: 27.17 | E44: =C44*D44 | G44: =C44*1.25*F44 | I44: =C44*1.5*H44 | K44: =C44*1.5*J44 | M44: =C44*1.75*L44 | O44: =C44*2*N44 | X44: =W44*X35 | Z44: =Y44*Z35 | AA44: =D44+F44+H44+J44+L44+N44 | AB44: =E44+G44+I44+K44+M44+O44+Z44+X44+V44+T44
A45: VONGSALY, Phimmasone (Apple) | C45: 27.17 | E45: =C45*D45 | G45: =C45*1.25*F45 | I45: =C45*1.5*H45 | K45: =C45*1.5*J45 | M45: =C45*1.75*L45 | O45: =C45*2*N45 | X45: =W45*X39 | Z45: =Y45*Z39 | AA45: =D45+F45+H45+J45+L45+N45 | AB45: =E45+G45+I45+K45+M45+O45+Z45+X45+V45+T45
A46: YONGBANTHOM, Siriprapa (Poppy) | C46: 27.17 | E46: =C46*D46 | G46: =C46*1.25*F46 | I46: =C46*1.5*H46 | K46: =C46*1.5*J46 | M46: =C46*1.75*L46 | O46: =C46*2*N46 | X46: =W46*X40 | Z46: =Y46*Z40 | AA46: =D46+F46+H46+J46+L46+N46 | AB46: =E46+G46+I46+K46+M46+O46+Z46+X46+V46+T46
A47: BEPPU, Yuji | C47: 24.98 | E47: =C47*D47 | G47: =C47*1.25*F47 | I47: =C47*1.5*H47 | K47: =C47*1.5*J47 | M47: =C47*1.75*L47 | O47: =C47*2*N47 | X47: =W47*X35 | Z47: =Y47*Z33 | AA47: =D47+F47+H47+J47+L47+N47 | AB47: =E47+G47+I47+K47+M47+O47+Z47+X47+V47+T47
A48: ANANTAPATTANAPONG, Jaruayporn (Jessie) | C48: 24.98 | E48: =C48*D48 | G48: =C48*1.25*F48 | I48: =C48*1.5*H48 | K48: =C48*1.5*J48 | M48: =C48*1.75*L48 | O48: =C48*2*N48 | X48: =W48*X35 | Z48: =Y48*Z34 | AA48: =D48+F48+H48+J48+L48+N48 | AB48: =E48+G48+I48+K48+M48+O48+Z48+X48+V48+T48
A49: PHONNARK, Chanakan (Pookpik) | C49: 25.8 | E49: =C49*D49 | G49: =C49*1.25*F49 | I49: =C49*1.5*H49 | K49: =C49*1.5*J49 | M49: =C49*1.75*L49 | O49: =C49*2*N49 | X49: =W49*X35 | Z49: =Y49*Z35 | AA49: =D49+F49+H49+J49+L49+N49 | AB49: =E49+G49+I49+K49+M49+O49+Z49+X49+V49+T49
C50: 0 | E50: =C50*D50 | G50: =C50*1.25*F50 | I50: =C50*1.5*H50 | K50: =C50*1.5*J50 | M50: =C50*1.75*L50 | O50: =C50*2*N50 | X50: =W50*X35 | Z50: =Y50*Z35 | AA50: =D50+F50+H50+J50+L50+N50 | AB50: =E50+G50+I50+K50+M50+O50+Z50+X50+V50+T50
AA51: =SUM(AA37:AA50) | AB51: =SUM(AB37:AB50)
A52: Transfer IN from NM
A53: EMPLOYEE | C53: RATE | D53: 1 | E53: $ | F53: 1.25 | G53: $ | H53: 1.5 | I53: $ | J53: 1.5 | K53: $ | L53: 1.75 | M53: $ | N53: 2 | O53: $ | P53: 2.25 | R53: 2.5 | S53: $ | T53: split | U53: sup | V53: laundry | X53: 2.48 | Z53: 3.71 | AA53: TOTAL | AB53: TOTAL
F54: SAT/cas ord | H54: SUN /Sat cas | J54: O/T | L54: SUN cas | N54: O/T | Q54: =C54*2.25*P54 | R54: ph casual
A55: Caleb | B55: Cas | C55: 15.51 | E55: =C55*D55 | G55: =C55*1.25*F55 | I55: =C55*1.5*H55 | K55: =C55*1.5*J55 | M55: =C55*1.75*L55 | O55: =C55*2*N55 | Q55: =C55*2.25*P55 | S55: =C55*2.5*R55 | X55: =W55*X53 | Z55: =Z50*Y55 | AA55: =D55+F55+H55+J55+L55+N55+R55 | AB55: =E55+G55+I55+K55+M55+O55+Z55+X55+V55+T55+S55
A56: SAPKOTA, Sanam | C56: 28.12 | E56: =C56*D56 | G56: =C56*1.25*F56 | I56: =C56*1.5*H56 | K56: =C56*1.5*J56 | M56: =C56*1.75*L56 | O56: =C56*2*N56 | Q56: =C56*2.25*P56 | S56: =C56*2.5*R56 | X56: =W56*X52 | Z56: =Z51*Y56 | AA56: =D56+F56+H56+J56+L56+N56 | AB56: =E56+G56+I56+K56+M56+O56+Z56+X56+V56+T56
A57: SHAIN | B57: Sal | C57: 32.73 | E57: =C57*D57 | G57: =C57*1.25*F57 | I57: =C57*1.5*H57 | K57: =C57*1.5*J57 | M57: =C57*1.75*L57 | O57: =C57*2*N57 | Q57: =C57*2.25*P57 | S57: =C57*2.5*R57 | X57: =W57*X53 | Z57: =Z52*Y57 | AA57: =D57+F57+H57+J57+L57+N57 | AB57: =E57+G57+I57+K57+M57+O57+Z57+X57+V57+T57
A58: Feige, Oliver | B58: cas | C58: 15.51 | E58: =C58*D58 | G58: =C58*1.25*F58 | I58: =C58*1.5*H58 | K58: =C58*1.5*J58 | M58: =C58*1.75*L58 | O58: =C58*2*N58 | Q58: =C58*2.25*P58 | S58: =C58*2.5*R58 | X58: =W58*X53 | Z58: =Z52*Y58 | AA58: =D58+F58+H58+J58+L58+N58+P58 | AB58: =S58+E58+G58+I58+K58+M58+O58+Z58+X58+V58+T58
A59: FERNANDES, Delisha | B59: SAL | C59: 39.48 | E59: =C59*D59 | G59: =C59*1.25*F59 | I59: =C59*1.5*H59 | K59: =C59*1.5*J59 | M59: =C59*1.75*L59 | O59: =C59*2*N59 | Q59: =C59*2.25*P59 | X59: =W59*X53 | Z59: =Z53*Y59 | AA59: =D59+F59+H59+J59+L59+N59+P59 | AB59: =Q59+E59+G59+I59+K59+M59+O59+Z59+X59+V59+T59
E60: =C60*D60 | G60: =C60*1.25*F60 | I60: =C60*1.5*H60 | K60: =C60*1.5*J60 | M60: =C60*1.75*L60 | O60: =C60*2*N60 | X60: =W60*X53 | Z60: =Z52*Y60 | AA60: =D60+F60+H60+J60+L60+N60 | AB60: =E60+G60+I60+K60+M60+O60+Z60+X60+V60+T60
Z61: =Z52*Y61 | AA61: =D61+F61+H61+J61+L61+N61 | AB61: =E61+G61+I61+K61+M61+O61+Z61+X61+V61+T61
A62: Skye | B62: CASUAL | C62: 20.82 | G62: =C62*F62*1.25 | I62: =C62*1.5*H62 | K62: =C62*1.5*J62 | M62: =C62*1.75*L62 | O62: =C62*2*N62 | X62: =X53*W62 | Z62: =Z53*Y62 | AA62: =D62+F62+H62+J62+L62+N62 | AB62: =E62+G62+I62+K62+M62+O62+Z62+X62+V62+T62
A63: Fico | B63: ROX | C63: 20.82 | E63: =C63*D63 | G63: =C63*1.25*F63 | I63: =C63*1.5*H63 | K63: =C63*1.5*J63 | M63: =C63*1.75*L63 | O63: =C63*2*N63 | X63: =X53*W63 | Z63: =Z53*Y63 | AA63: =D63+F63+H63+J63+L63+N63 | AB63: =E63+G63+I63+K63+M63+O63+Z63+X63+V63+T63
AA64: =SUM(AA55:AA63) | AB64: =SUM(AB55:AB63)
A65: Transfer IN from BH
A66: EMPLOYEE | C66: RATE | D66: 1 | E66: $ | F66: 1.25 | G66: $ | H66: 1.5 | I66: $ | J66: 1.5 | K66: $ | L66: 1.75 | M66: $ | N66: 2 | O66: $ | P66: 2.25 | R66: 2.5 | T66: split | U66: sup | V66: laundry | W66: 10-12am | X66: 2.81 | Z66: 4.22 | AA66: TOTAL | AB66: TOTAL
F67: SAT | H67: SUN | J67: O/T | L67: O/T | N67: O/T
A68: LAMA, Bishal | C68: 28.12 | E68: =C68*D68 | G68: =C68*1.25*F68 | I68: =C68*1.5*H68 | K68: =C68*1.5*J68 | M68: =C68*1.75*L68 | O68: =C68*2*N68 | Q68: =C68*2.25*P68 | S68: 0 | X68: =W68*X66 | Z68: =Z66*Y68 | AA68: =D68+P68+R68+F68+H68+J68+L68+N68 | AB68: =E68+G68+I68+K68+M68+O68+Z68+X68+V68+T68+Q68+S68
A69: PAKWAL, Ashim | B69: SAL | C69: 37.45 | E69: =C69*D69 | G69: =C69*1.25*F69 | I69: =C69*1.5*H69 | K69: =C69*1.5*J69 | M69: =C69*1.75*L69 | O69: =C69*2*N69 | Q69: =C69*2.25*P69 | S69: =C69*2.5*R69 | X69: =W69*X66 | Z69: =Z66*Y69 | AA69: =D69+F69+H69+J69+L69+N69 | AB69: =E69+G69+I69+K69+M69+O69+Z69+X69+V69+Q69+S69+T69+U69
A70: SEDHAI, Aayush | B70: SAL | C70: 35.45 | E70: =C70*D70 | G70: =C70*1.25*F70 | I70: =C70*1.5*H70 | K70: =C70*1.5*J70 | M70: =C70*1.75*L70 | O70: =C70*2*N70 | Q70: =C70*2.25*P70 | S70: =C70*2.5*R70 | Z70: =Z66*Y70 | AA70: =D70+F70+H70+J70+L70+N70+P70 | AB70: =E70+G70+I70+K70+M70+O70+Z70+X73+V70+Q70+S70+T70+U70
A71: THAPA, Sonam | C71: 28.12 | E71: =C71*D71 | G71: =C71*1.25*F71 | I71: =C71*1.5*H71 | K71: =C71*1.5*J71 | M71: =C71*1.75*L71 | O71: =C71*2*N71 | Q71: =C71*2.25*P71 | S71: =C71*2.5*R71 | X71: =W71*X66 | Z71: =Y71*Z66 | AA71: =D71+F71+H71+J72+L72+N72+P72 | AB71: =E71+G71+I71+K72+M72+O72+Z71+X71+V71+Q72+T71+U71
A72: LAMA, Bishal | C72: 24.76 | K72: =C72*1.5*J72 | M72: =C72*1.75*L72 | O72: =C72*2*N72 | Q72: =C72*2.25*P72 | S72: =C72*2.5*R72 | X72: =W72*X67
A73: Harsh | C73: 27.17 | E73: =C73*D73 | G73: =C73*1.25*F73 | I73: =C73*1.5*H73 | K73: =C73*1.5*J73 | M73: =C73*1.75*L73 | O73: =C73*2*N73 | Q73: =C73*2.25*P73 | S73: =C73*2.5*R73 | X73: =W73*X66 | Z73: =Y73*Z66 | AA73: =D73+P73+R73+F73+H73+J73+L73+N73 | AB73: =E73+G73+I73+K73+M73+O73+Z73+X73+V73+Q73+S73+T73+U73
A74: Tuerah Caleb (Jr) | C74: 12.97 | E74: =C74*D74 | G74: =C74*1.25*F74 | I74: =C74*1.5*H74 | K74: =C74*1.5*J74 | M74: =C74*1.75*L74 | O74: =C74*2*N74 | Q74: =C74*2.25*P74 | S74: =C74*2.5*R74 | X74: =W74*X69 | Z74: =Y74*Z66 | AA74: =D74+P74+R74+F74+H74+J74+L74+N74 | AB74: =E74+G74+I74+K74+M74+O74+Z74+X74+V74+Q74+S74+T74+U74
A75: KAUSHIK, Saloni | C75: 24.98 | E75: =C75*D75 | G75: =C75*1.25*F75 | I75: =C75*1.5*H75 | K75: =C75*1.5*J75 | M75: =C75*1.75*L75 | O75: =C75*2*N75 | Q75: =C75*2.25*P75 | S75: =C75*2.5*R75 | X75: =W75*X66 | Z75: =Y75*Z66 | AA75: =D75+P75+R75+F75+H75+J75+L75+N75 | AB75: =E75+G75+I75+K75+M75+O75+Z75+X75+V75+Q75+S75+T75+U75
A76: SHERPA, Sonam | C76: 25.8 | E76: =C76*D76 | G76: =C76*1.25*F76 | I76: =C76*1.5*H76 | K76: =C76*1.5*J76 | M76: =C76*1.75*L76 | O76: =C76*2*N76 | Q76: =C76*2.25*P76 | S76: 0 | X76: =W76*X66 | Z76: =Y76*Z66 | AA76: =D76+P76+R76+F76+H76+J76+L76+N76 | AB76: =E76+G76+I76+K76+M76+O76+Z76+X76+V76+T76+Q76+S76
X77: =W77*X68 | AA77: =SUM(AA67:AA76) | AB77: =SUM(AB67:AB76)
